<?xml version="1.0" encoding="utf-8"?>
<?xml-stylesheet type="text/xsl" href="https://www.floatrates.com/currency-rates.xsl" ?>
<channel>
	<title>XML Historical Foreign Exchange Rates for Swiss Franc (CHF) (22 Mar 2018)</title>
	<link>http://www.floatrates.com/currency/chf/</link>
	<xmlLink>http://www.floatrates.com/daily/chf.xml</xmlLink>
	<description>XML historical foreign exchange rates for Swiss Franc (CHF) from the Float Rates. Published at 22 Mar 2018.</description>
	<language>en</language>
	<baseCurrency>CHF</baseCurrency>
	<pubDate>Thu, 22 Mar 2018</pubDate>
	<lastBuildDate>Thu, 22 Mar 2018</lastBuildDate>
	
	<item>
		<title>1 CHF = 0.396454 BHD</title>
		<link>http://www.floatrates.com/chf/bhd/</link>
		<description>1 Swiss Franc = 0.396454 Bahrain Dinar</description>
		<pubDate></pubDate>
		<baseCurrency>CHF</baseCurrency>
		<baseName>Swiss Franc</baseName>
		<targetCurrency>BHD</targetCurrency>
		<targetName>Bahrain Dinar</targetName>
		<exchangeRate>0.396454</exchangeRate>
		<inverseRate>2.522360</inverseRate>
		<inverseDescription>1 Bahrain Dinar = 2.522360 Swiss Franc</inverseDescription>
	</item>
	<item>
		<title>1 CHF = 1.364402 AUD</title>
		<link>http://www.floatrates.com/chf/aud/</link>
		<description>1 Swiss Franc = 1.364402 Australian Dollar</description>
		<pubDate></pubDate>
		<baseCurrency>CHF</baseCurrency>
		<baseName>Swiss Franc</baseName>
		<targetCurrency>AUD</targetCurrency>
		<targetName>Australian Dollar</targetName>
		<exchangeRate>1.364402</exchangeRate>
		<inverseRate>0.732922</inverseRate>
		<inverseDescription>1 Australian Dollar = 0.732922 Swiss Franc</inverseDescription>
	</item>
	<item>
		<title>1 CHF = 0.855469 EUR</title>
		<link>http://www.floatrates.com/chf/eur/</link>
		<description>1 Swiss Franc = 0.855469 Euro</description>
		<pubDate></pubDate>
		<baseCurrency>CHF</baseCurrency>
		<baseName>Swiss Franc</baseName>
		<targetCurrency>EUR</targetCurrency>
		<targetName>Euro</targetName>
		<exchangeRate>0.855469</exchangeRate>
		<inverseRate>1.168949</inverseRate>
		<inverseDescription>1 Euro = 1.168949 Swiss Franc</inverseDescription>
	</item>
	<item>
		<title>1 CHF = 0.745422 GBP</title>
		<link>http://www.floatrates.com/chf/gbp/</link>
		<description>1 Swiss Franc = 0.745422 U.K. Pound Sterling</description>
		<pubDate></pubDate>
		<baseCurrency>CHF</baseCurrency>
		<baseName>Swiss Franc</baseName>
		<targetCurrency>GBP</targetCurrency>
		<targetName>U.K. Pound Sterling</targetName>
		<exchangeRate>0.745422</exchangeRate>
		<inverseRate>1.341521</inverseRate>
		<inverseDescription>1 U.K. Pound Sterling = 1.341521 Swiss Franc</inverseDescription>
	</item>
	<item>
		<title>1 CHF = 1.054657 USD</title>
		<link>http://www.floatrates.com/chf/usd/</link>
		<description>1 Swiss Franc = 1.054657 U.S. Dollar</description>
		<pubDate></pubDate>
		<baseCurrency>CHF</baseCurrency>
		<baseName>Swiss Franc</baseName>
		<targetCurrency>USD</targetCurrency>
		<targetName>U.S. Dollar</targetName>
		<exchangeRate>1.054657</exchangeRate>
		<inverseRate>0.948175</inverseRate>
		<inverseDescription>1 U.S. Dollar = 0.948175 Swiss Franc</inverseDescription>
	</item>
	<item>
		<title>1 CHF = 32.633783 NIO</title>
		<link>http://www.floatrates.com/chf/nio/</link>
		<description>1 Swiss Franc = 32.633783 Nicaraguan Córdoba</description>
		<pubDate></pubDate>
		<baseCurrency>CHF</baseCurrency>
		<baseName>Swiss Franc</baseName>
		<targetCurrency>NIO</targetCurrency>
		<targetName>Nicaraguan Córdoba</targetName>
		<exchangeRate>32.633783</exchangeRate>
		<inverseRate>0.030643</inverseRate>
		<inverseDescription>1 Nicaraguan Córdoba = 0.030643 Swiss Franc</inverseDescription>
	</item>
	<item>
		<title>1 CHF = 6.672086 CNY</title>
		<link>http://www.floatrates.com/chf/cny/</link>
		<description>1 Swiss Franc = 6.672086 Chinese Yuan</description>
		<pubDate></pubDate>
		<baseCurrency>CHF</baseCurrency>
		<baseName>Swiss Franc</baseName>
		<targetCurrency>CNY</targetCurrency>
		<targetName>Chinese Yuan</targetName>
		<exchangeRate>6.672086</exchangeRate>
		<inverseRate>0.149878</inverseRate>
		<inverseDescription>1 Chinese Yuan = 0.149878 Swiss Franc</inverseDescription>
	</item>
	<item>
		<title>1 CHF = 111.386689 JPY</title>
		<link>http://www.floatrates.com/chf/jpy/</link>
		<description>1 Swiss Franc = 111.386689 Japanese Yen</description>
		<pubDate></pubDate>
		<baseCurrency>CHF</baseCurrency>
		<baseName>Swiss Franc</baseName>
		<targetCurrency>JPY</targetCurrency>
		<targetName>Japanese Yen</targetName>
		<exchangeRate>111.386689</exchangeRate>
		<inverseRate>0.008978</inverseRate>
		<inverseDescription>1 Japanese Yen = 0.008978 Swiss Franc</inverseDescription>
	</item>
	<item>
		<title>1 CHF = 1,134.168317 KRW</title>
		<link>http://www.floatrates.com/chf/krw/</link>
		<description>1 Swiss Franc = 1,134.168317 South Korean Won</description>
		<pubDate></pubDate>
		<baseCurrency>CHF</baseCurrency>
		<baseName>Swiss Franc</baseName>
		<targetCurrency>KRW</targetCurrency>
		<targetName>South Korean Won</targetName>
		<exchangeRate>1,134.168317</exchangeRate>
		<inverseRate>0.000882</inverseRate>
		<inverseDescription>1 South Korean Won = 0.000882 Swiss Franc</inverseDescription>
	</item>
	<item>
		<title>1 CHF = 1.386184 SGD</title>
		<link>http://www.floatrates.com/chf/sgd/</link>
		<description>1 Swiss Franc = 1.386184 Singapore Dollar</description>
		<pubDate></pubDate>
		<baseCurrency>CHF</baseCurrency>
		<baseName>Swiss Franc</baseName>
		<targetCurrency>SGD</targetCurrency>
		<targetName>Singapore Dollar</targetName>
		<exchangeRate>1.386184</exchangeRate>
		<inverseRate>0.721405</inverseRate>
		<inverseDescription>1 Singapore Dollar = 0.721405 Swiss Franc</inverseDescription>
	</item>
	<item>
		<title>1 CHF = 1.458223 NZD</title>
		<link>http://www.floatrates.com/chf/nzd/</link>
		<description>1 Swiss Franc = 1.458223 New Zealand Dollar</description>
		<pubDate></pubDate>
		<baseCurrency>CHF</baseCurrency>
		<baseName>Swiss Franc</baseName>
		<targetCurrency>NZD</targetCurrency>
		<targetName>New Zealand Dollar</targetName>
		<exchangeRate>1.458223</exchangeRate>
		<inverseRate>0.685766</inverseRate>
		<inverseDescription>1 New Zealand Dollar = 0.685766 Swiss Franc</inverseDescription>
	</item>
	<item>
		<title>1 CHF = 4.125300 MYR</title>
		<link>http://www.floatrates.com/chf/myr/</link>
		<description>1 Swiss Franc = 4.125300 Malaysian Ringgit</description>
		<pubDate></pubDate>
		<baseCurrency>CHF</baseCurrency>
		<baseName>Swiss Franc</baseName>
		<targetCurrency>MYR</targetCurrency>
		<targetName>Malaysian Ringgit</targetName>
		<exchangeRate>4.125300</exchangeRate>
		<inverseRate>0.242407</inverseRate>
		<inverseDescription>1 Malaysian Ringgit = 0.242407 Swiss Franc</inverseDescription>
	</item>
	<item>
		<title>1 CHF = 32.933194 THB</title>
		<link>http://www.floatrates.com/chf/thb/</link>
		<description>1 Swiss Franc = 32.933194 Thai Baht</description>
		<pubDate></pubDate>
		<baseCurrency>CHF</baseCurrency>
		<baseName>Swiss Franc</baseName>
		<targetCurrency>THB</targetCurrency>
		<targetName>Thai Baht</targetName>
		<exchangeRate>32.933194</exchangeRate>
		<inverseRate>0.030365</inverseRate>
		<inverseDescription>1 Thai Baht = 0.030365 Swiss Franc</inverseDescription>
	</item>
	<item>
		<title>1 CHF = 14,489.754732 IDR</title>
		<link>http://www.floatrates.com/chf/idr/</link>
		<description>1 Swiss Franc = 14,489.754732 Indonesian Rupiah</description>
		<pubDate></pubDate>
		<baseCurrency>CHF</baseCurrency>
		<baseName>Swiss Franc</baseName>
		<targetCurrency>IDR</targetCurrency>
		<targetName>Indonesian Rupiah</targetName>
		<exchangeRate>14,489.754732</exchangeRate>
		<inverseRate>0.000069</inverseRate>
		<inverseDescription>1 Indonesian Rupiah = 0.000069 Swiss Franc</inverseDescription>
	</item>
	<item>
		<title>1 CHF = 68.648590 INR</title>
		<link>http://www.floatrates.com/chf/inr/</link>
		<description>1 Swiss Franc = 68.648590 Indian Rupee</description>
		<pubDate></pubDate>
		<baseCurrency>CHF</baseCurrency>
		<baseName>Swiss Franc</baseName>
		<targetCurrency>INR</targetCurrency>
		<targetName>Indian Rupee</targetName>
		<exchangeRate>68.648590</exchangeRate>
		<inverseRate>0.014567</inverseRate>
		<inverseDescription>1 Indian Rupee = 0.014567 Swiss Franc</inverseDescription>
	</item>
	<item>
		<title>1 CHF = 30.739919 TWD</title>
		<link>http://www.floatrates.com/chf/twd/</link>
		<description>1 Swiss Franc = 30.739919 New Taiwan Dollar </description>
		<pubDate></pubDate>
		<baseCurrency>CHF</baseCurrency>
		<baseName>Swiss Franc</baseName>
		<targetCurrency>TWD</targetCurrency>
		<targetName>New Taiwan Dollar </targetName>
		<exchangeRate>30.739919</exchangeRate>
		<inverseRate>0.032531</inverseRate>
		<inverseDescription>1 New Taiwan Dollar  = 0.032531 Swiss Franc</inverseDescription>
	</item>
	<item>
		<title>1 CHF = 23,957.984685 VND</title>
		<link>http://www.floatrates.com/chf/vnd/</link>
		<description>1 Swiss Franc = 23,957.984685 Vietnamese Dong</description>
		<pubDate></pubDate>
		<baseCurrency>CHF</baseCurrency>
		<baseName>Swiss Franc</baseName>
		<targetCurrency>VND</targetCurrency>
		<targetName>Vietnamese Dong</targetName>
		<exchangeRate>23,957.984685</exchangeRate>
		<inverseRate>0.000042</inverseRate>
		<inverseDescription>1 Vietnamese Dong = 0.000042 Swiss Franc</inverseDescription>
	</item>
	<item>
		<title>1 CHF = 8.275794 HKD</title>
		<link>http://www.floatrates.com/chf/hkd/</link>
		<description>1 Swiss Franc = 8.275794 Hong Kong Dollar</description>
		<pubDate></pubDate>
		<baseCurrency>CHF</baseCurrency>
		<baseName>Swiss Franc</baseName>
		<targetCurrency>HKD</targetCurrency>
		<targetName>Hong Kong Dollar</targetName>
		<exchangeRate>8.275794</exchangeRate>
		<inverseRate>0.120834</inverseRate>
		<inverseDescription>1 Hong Kong Dollar = 0.120834 Swiss Franc</inverseDescription>
	</item>
	<item>
		<title>1 CHF = 3.428617 PGK</title>
		<link>http://www.floatrates.com/chf/pgk/</link>
		<description>1 Swiss Franc = 3.428617 Papua New Guinean kina</description>
		<pubDate></pubDate>
		<baseCurrency>CHF</baseCurrency>
		<baseName>Swiss Franc</baseName>
		<targetCurrency>PGK</targetCurrency>
		<targetName>Papua New Guinean kina</targetName>
		<exchangeRate>3.428617</exchangeRate>
		<inverseRate>0.291663</inverseRate>
		<inverseDescription>1 Papua New Guinean kina = 0.291663 Swiss Franc</inverseDescription>
	</item>
	<item>
		<title>1 CHF = 1.000000 CHF</title>
		<link>http://www.floatrates.com/chf/chf/</link>
		<description>1 Swiss Franc = 1.000000 Swiss Franc</description>
		<pubDate></pubDate>
		<baseCurrency>CHF</baseCurrency>
		<baseName>Swiss Franc</baseName>
		<targetCurrency>CHF</targetCurrency>
		<targetName>Swiss Franc</targetName>
		<exchangeRate>1.000000</exchangeRate>
		<inverseRate>1.000000</inverseRate>
		<inverseDescription>1 Swiss Franc = 1.000000 Swiss Franc</inverseDescription>
	</item>
	<item>
		<title>1 CHF = 3.872546 AED</title>
		<link>http://www.floatrates.com/chf/aed/</link>
		<description>1 Swiss Franc = 3.872546 U.A.E Dirham</description>
		<pubDate></pubDate>
		<baseCurrency>CHF</baseCurrency>
		<baseName>Swiss Franc</baseName>
		<targetCurrency>AED</targetCurrency>
		<targetName>U.A.E Dirham</targetName>
		<exchangeRate>3.872546</exchangeRate>
		<inverseRate>0.258228</inverseRate>
		<inverseDescription>1 U.A.E Dirham = 0.258228 Swiss Franc</inverseDescription>
	</item>
	<item>
		<title>1 CHF = 1.365345 CAD</title>
		<link>http://www.floatrates.com/chf/cad/</link>
		<description>1 Swiss Franc = 1.365345 Canadian Dollar</description>
		<pubDate></pubDate>
		<baseCurrency>CHF</baseCurrency>
		<baseName>Swiss Franc</baseName>
		<targetCurrency>CAD</targetCurrency>
		<targetName>Canadian Dollar</targetName>
		<exchangeRate>1.365345</exchangeRate>
		<inverseRate>0.732416</inverseRate>
		<inverseDescription>1 Canadian Dollar = 0.732416 Swiss Franc</inverseDescription>
	</item>
	<item>
		<title>1 CHF = 266.556473 HUF</title>
		<link>http://www.floatrates.com/chf/huf/</link>
		<description>1 Swiss Franc = 266.556473 Hungarian Forint</description>
		<pubDate></pubDate>
		<baseCurrency>CHF</baseCurrency>
		<baseName>Swiss Franc</baseName>
		<targetCurrency>HUF</targetCurrency>
		<targetName>Hungarian Forint</targetName>
		<exchangeRate>266.556473</exchangeRate>
		<inverseRate>0.003752</inverseRate>
		<inverseDescription>1 Hungarian Forint = 0.003752 Swiss Franc</inverseDescription>
	</item>
	<item>
		<title>1 CHF = 27.717139 UAH</title>
		<link>http://www.floatrates.com/chf/uah/</link>
		<description>1 Swiss Franc = 27.717139 Ukrainian Hryvnia</description>
		<pubDate></pubDate>
		<baseCurrency>CHF</baseCurrency>
		<baseName>Swiss Franc</baseName>
		<targetCurrency>UAH</targetCurrency>
		<targetName>Ukrainian Hryvnia</targetName>
		<exchangeRate>27.717139</exchangeRate>
		<inverseRate>0.036079</inverseRate>
		<inverseDescription>1 Ukrainian Hryvnia = 0.036079 Swiss Franc</inverseDescription>
	</item>
	<item>
		<title>1 CHF = 21.746461 CZK</title>
		<link>http://www.floatrates.com/chf/czk/</link>
		<description>1 Swiss Franc = 21.746461 Czech Koruna</description>
		<pubDate></pubDate>
		<baseCurrency>CHF</baseCurrency>
		<baseName>Swiss Franc</baseName>
		<targetCurrency>CZK</targetCurrency>
		<targetName>Czech Koruna</targetName>
		<exchangeRate>21.746461</exchangeRate>
		<inverseRate>0.045984</inverseRate>
		<inverseDescription>1 Czech Koruna = 0.045984 Swiss Franc</inverseDescription>
	</item>
	<item>
		<title>1 CHF = 6.377269 DKK</title>
		<link>http://www.floatrates.com/chf/dkk/</link>
		<description>1 Swiss Franc = 6.377269 Danish Krone</description>
		<pubDate></pubDate>
		<baseCurrency>CHF</baseCurrency>
		<baseName>Swiss Franc</baseName>
		<targetCurrency>DKK</targetCurrency>
		<targetName>Danish Krone</targetName>
		<exchangeRate>6.377269</exchangeRate>
		<inverseRate>0.156807</inverseRate>
		<inverseDescription>1 Danish Krone = 0.156807 Swiss Franc</inverseDescription>
	</item>
	<item>
		<title>1 CHF = 105.030259 ISK</title>
		<link>http://www.floatrates.com/chf/isk/</link>
		<description>1 Swiss Franc = 105.030259 Icelandic Krona</description>
		<pubDate></pubDate>
		<baseCurrency>CHF</baseCurrency>
		<baseName>Swiss Franc</baseName>
		<targetCurrency>ISK</targetCurrency>
		<targetName>Icelandic Krona</targetName>
		<exchangeRate>105.030259</exchangeRate>
		<inverseRate>0.009521</inverseRate>
		<inverseDescription>1 Icelandic Krona = 0.009521 Swiss Franc</inverseDescription>
	</item>
	<item>
		<title>1 CHF = 8.161428 NOK</title>
		<link>http://www.floatrates.com/chf/nok/</link>
		<description>1 Swiss Franc = 8.161428 Norwegian Krone</description>
		<pubDate></pubDate>
		<baseCurrency>CHF</baseCurrency>
		<baseName>Swiss Franc</baseName>
		<targetCurrency>NOK</targetCurrency>
		<targetName>Norwegian Krone</targetName>
		<exchangeRate>8.161428</exchangeRate>
		<inverseRate>0.122528</inverseRate>
		<inverseDescription>1 Norwegian Krone = 0.122528 Swiss Franc</inverseDescription>
	</item>
	<item>
		<title>1 CHF = 8.656407 SEK</title>
		<link>http://www.floatrates.com/chf/sek/</link>
		<description>1 Swiss Franc = 8.656407 Swedish Krona</description>
		<pubDate></pubDate>
		<baseCurrency>CHF</baseCurrency>
		<baseName>Swiss Franc</baseName>
		<targetCurrency>SEK</targetCurrency>
		<targetName>Swedish Krona</targetName>
		<exchangeRate>8.656407</exchangeRate>
		<inverseRate>0.115521</inverseRate>
		<inverseDescription>1 Swedish Krona = 0.115521 Swiss Franc</inverseDescription>
	</item>
	<item>
		<title>1 CHF = 6.373469 HRK</title>
		<link>http://www.floatrates.com/chf/hrk/</link>
		<description>1 Swiss Franc = 6.373469 Croatian Kuna</description>
		<pubDate></pubDate>
		<baseCurrency>CHF</baseCurrency>
		<baseName>Swiss Franc</baseName>
		<targetCurrency>HRK</targetCurrency>
		<targetName>Croatian Kuna</targetName>
		<exchangeRate>6.373469</exchangeRate>
		<inverseRate>0.156900</inverseRate>
		<inverseDescription>1 Croatian Kuna = 0.156900 Swiss Franc</inverseDescription>
	</item>
	<item>
		<title>1 CHF = 3.995351 RON</title>
		<link>http://www.floatrates.com/chf/ron/</link>
		<description>1 Swiss Franc = 3.995351 Romanian New Leu</description>
		<pubDate></pubDate>
		<baseCurrency>CHF</baseCurrency>
		<baseName>Swiss Franc</baseName>
		<targetCurrency>RON</targetCurrency>
		<targetName>Romanian New Leu</targetName>
		<exchangeRate>3.995351</exchangeRate>
		<inverseRate>0.250291</inverseRate>
		<inverseDescription>1 Romanian New Leu = 0.250291 Swiss Franc</inverseDescription>
	</item>
	<item>
		<title>1 CHF = 1.674219 BGN</title>
		<link>http://www.floatrates.com/chf/bgn/</link>
		<description>1 Swiss Franc = 1.674219 Bulgarian Lev</description>
		<pubDate></pubDate>
		<baseCurrency>CHF</baseCurrency>
		<baseName>Swiss Franc</baseName>
		<targetCurrency>BGN</targetCurrency>
		<targetName>Bulgarian Lev</targetName>
		<exchangeRate>1.674219</exchangeRate>
		<inverseRate>0.597293</inverseRate>
		<inverseDescription>1 Bulgarian Lev = 0.597293 Swiss Franc</inverseDescription>
	</item>
	<item>
		<title>1 CHF = 4.143601 TRY</title>
		<link>http://www.floatrates.com/chf/try/</link>
		<description>1 Swiss Franc = 4.143601 Turkish Lira</description>
		<pubDate></pubDate>
		<baseCurrency>CHF</baseCurrency>
		<baseName>Swiss Franc</baseName>
		<targetCurrency>TRY</targetCurrency>
		<targetName>Turkish Lira</targetName>
		<exchangeRate>4.143601</exchangeRate>
		<inverseRate>0.241336</inverseRate>
		<inverseDescription>1 Turkish Lira = 0.241336 Swiss Franc</inverseDescription>
	</item>
	<item>
		<title>1 CHF = 3.673400 ILS</title>
		<link>http://www.floatrates.com/chf/ils/</link>
		<description>1 Swiss Franc = 3.673400 Israeli New Sheqel</description>
		<pubDate></pubDate>
		<baseCurrency>CHF</baseCurrency>
		<baseName>Swiss Franc</baseName>
		<targetCurrency>ILS</targetCurrency>
		<targetName>Israeli New Sheqel</targetName>
		<exchangeRate>3.673400</exchangeRate>
		<inverseRate>0.272227</inverseRate>
		<inverseDescription>1 Israeli New Sheqel = 0.272227 Swiss Franc</inverseDescription>
	</item>
	<item>
		<title>1 CHF = 640.269954 CLP</title>
		<link>http://www.floatrates.com/chf/clp/</link>
		<description>1 Swiss Franc = 640.269954 Chilean Peso</description>
		<pubDate></pubDate>
		<baseCurrency>CHF</baseCurrency>
		<baseName>Swiss Franc</baseName>
		<targetCurrency>CLP</targetCurrency>
		<targetName>Chilean Peso</targetName>
		<exchangeRate>640.269954</exchangeRate>
		<inverseRate>0.001562</inverseRate>
		<inverseDescription>1 Chilean Peso = 0.001562 Swiss Franc</inverseDescription>
	</item>
	<item>
		<title>1 CHF = 55.269918 PHP</title>
		<link>http://www.floatrates.com/chf/php/</link>
		<description>1 Swiss Franc = 55.269918 Philippine Peso</description>
		<pubDate></pubDate>
		<baseCurrency>CHF</baseCurrency>
		<baseName>Swiss Franc</baseName>
		<targetCurrency>PHP</targetCurrency>
		<targetName>Philippine Peso</targetName>
		<exchangeRate>55.269918</exchangeRate>
		<inverseRate>0.018093</inverseRate>
		<inverseDescription>1 Philippine Peso = 0.018093 Swiss Franc</inverseDescription>
	</item>
	<item>
		<title>1 CHF = 19.517679 MXN</title>
		<link>http://www.floatrates.com/chf/mxn/</link>
		<description>1 Swiss Franc = 19.517679 Mexican Peso</description>
		<pubDate></pubDate>
		<baseCurrency>CHF</baseCurrency>
		<baseName>Swiss Franc</baseName>
		<targetCurrency>MXN</targetCurrency>
		<targetName>Mexican Peso</targetName>
		<exchangeRate>19.517679</exchangeRate>
		<inverseRate>0.051236</inverseRate>
		<inverseDescription>1 Mexican Peso = 0.051236 Swiss Franc</inverseDescription>
	</item>
	<item>
		<title>1 CHF = 12.466256 ZAR</title>
		<link>http://www.floatrates.com/chf/zar/</link>
		<description>1 Swiss Franc = 12.466256 South African Rand</description>
		<pubDate></pubDate>
		<baseCurrency>CHF</baseCurrency>
		<baseName>Swiss Franc</baseName>
		<targetCurrency>ZAR</targetCurrency>
		<targetName>South African Rand</targetName>
		<exchangeRate>12.466256</exchangeRate>
		<inverseRate>0.080217</inverseRate>
		<inverseDescription>1 South African Rand = 0.080217 Swiss Franc</inverseDescription>
	</item>
	<item>
		<title>1 CHF = 3.479004 BRL</title>
		<link>http://www.floatrates.com/chf/brl/</link>
		<description>1 Swiss Franc = 3.479004 Brazilian Real</description>
		<pubDate></pubDate>
		<baseCurrency>CHF</baseCurrency>
		<baseName>Swiss Franc</baseName>
		<targetCurrency>BRL</targetCurrency>
		<targetName>Brazilian Real</targetName>
		<exchangeRate>3.479004</exchangeRate>
		<inverseRate>0.287439</inverseRate>
		<inverseDescription>1 Brazilian Real = 0.287439 Swiss Franc</inverseDescription>
	</item>
	<item>
		<title>1 CHF = 60.112244 RUB</title>
		<link>http://www.floatrates.com/chf/rub/</link>
		<description>1 Swiss Franc = 60.112244 Russian Rouble</description>
		<pubDate></pubDate>
		<baseCurrency>CHF</baseCurrency>
		<baseName>Swiss Franc</baseName>
		<targetCurrency>RUB</targetCurrency>
		<targetName>Russian Rouble</targetName>
		<exchangeRate>60.112244</exchangeRate>
		<inverseRate>0.016636</inverseRate>
		<inverseDescription>1 Russian Rouble = 0.016636 Swiss Franc</inverseDescription>
	</item>
	<item>
		<title>1 CHF = 72.663038 AFN</title>
		<link>http://www.floatrates.com/chf/afn/</link>
		<description>1 Swiss Franc = 72.663038 Afghan afghani</description>
		<pubDate></pubDate>
		<baseCurrency>CHF</baseCurrency>
		<baseName>Swiss Franc</baseName>
		<targetCurrency>AFN</targetCurrency>
		<targetName>Afghan afghani</targetName>
		<exchangeRate>72.663038</exchangeRate>
		<inverseRate>0.013762</inverseRate>
		<inverseDescription>1 Afghan afghani = 0.013762 Swiss Franc</inverseDescription>
	</item>
	<item>
		<title>1 CHF = 3,380.428630 MGA</title>
		<link>http://www.floatrates.com/chf/mga/</link>
		<description>1 Swiss Franc = 3,380.428630 Malagasy ariary</description>
		<pubDate></pubDate>
		<baseCurrency>CHF</baseCurrency>
		<baseName>Swiss Franc</baseName>
		<targetCurrency>MGA</targetCurrency>
		<targetName>Malagasy ariary</targetName>
		<exchangeRate>3,380.428630</exchangeRate>
		<inverseRate>0.000296</inverseRate>
		<inverseDescription>1 Malagasy ariary = 0.000296 Swiss Franc</inverseDescription>
	</item>
	<item>
		<title>1 CHF = 1.046109 PAB</title>
		<link>http://www.floatrates.com/chf/pab/</link>
		<description>1 Swiss Franc = 1.046109 Panamanian Balboa</description>
		<pubDate></pubDate>
		<baseCurrency>CHF</baseCurrency>
		<baseName>Swiss Franc</baseName>
		<targetCurrency>PAB</targetCurrency>
		<targetName>Panamanian Balboa</targetName>
		<exchangeRate>1.046109</exchangeRate>
		<inverseRate>0.955924</inverseRate>
		<inverseDescription>1 Panamanian Balboa = 0.955924 Swiss Franc</inverseDescription>
	</item>
	<item>
		<title>1 CHF = 28.679986 ETB</title>
		<link>http://www.floatrates.com/chf/etb/</link>
		<description>1 Swiss Franc = 28.679986 Ethiopian birr</description>
		<pubDate></pubDate>
		<baseCurrency>CHF</baseCurrency>
		<baseName>Swiss Franc</baseName>
		<targetCurrency>ETB</targetCurrency>
		<targetName>Ethiopian birr</targetName>
		<exchangeRate>28.679986</exchangeRate>
		<inverseRate>0.034868</inverseRate>
		<inverseDescription>1 Ethiopian birr = 0.034868 Swiss Franc</inverseDescription>
	</item>
	<item>
		<title>1 CHF = 46,030.112553 VEF</title>
		<link>http://www.floatrates.com/chf/vef/</link>
		<description>1 Swiss Franc = 46,030.112553 Venezuelan Bolivar (till 20 August 2018)</description>
		<pubDate></pubDate>
		<baseCurrency>CHF</baseCurrency>
		<baseName>Swiss Franc</baseName>
		<targetCurrency>VEF</targetCurrency>
		<targetName>Venezuelan Bolivar (till 20 August 2018)</targetName>
		<exchangeRate>46,030.112553</exchangeRate>
		<inverseRate>0.000022</inverseRate>
		<inverseDescription>1 Venezuelan Bolivar (till 20 August 2018) = 0.000022 Swiss Franc</inverseDescription>
	</item>
	<item>
		<title>1 CHF = 7.243853 BOB</title>
		<link>http://www.floatrates.com/chf/bob/</link>
		<description>1 Swiss Franc = 7.243853 Bolivian Boliviano</description>
		<pubDate></pubDate>
		<baseCurrency>CHF</baseCurrency>
		<baseName>Swiss Franc</baseName>
		<targetCurrency>BOB</targetCurrency>
		<targetName>Bolivian Boliviano</targetName>
		<exchangeRate>7.243853</exchangeRate>
		<inverseRate>0.138048</inverseRate>
		<inverseDescription>1 Bolivian Boliviano = 0.138048 Swiss Franc</inverseDescription>
	</item>
	<item>
		<title>1 CHF = 593.441398 CRC</title>
		<link>http://www.floatrates.com/chf/crc/</link>
		<description>1 Swiss Franc = 593.441398 Costa Rican Colón</description>
		<pubDate></pubDate>
		<baseCurrency>CHF</baseCurrency>
		<baseName>Swiss Franc</baseName>
		<targetCurrency>CRC</targetCurrency>
		<targetName>Costa Rican Colón</targetName>
		<exchangeRate>593.441398</exchangeRate>
		<inverseRate>0.001685</inverseRate>
		<inverseDescription>1 Costa Rican Colón = 0.001685 Swiss Franc</inverseDescription>
	</item>
	<item>
		<title>1 CHF = 9.160148 SVC</title>
		<link>http://www.floatrates.com/chf/svc/</link>
		<description>1 Swiss Franc = 9.160148 Salvadoran colon</description>
		<pubDate></pubDate>
		<baseCurrency>CHF</baseCurrency>
		<baseName>Swiss Franc</baseName>
		<targetCurrency>SVC</targetCurrency>
		<targetName>Salvadoran colon</targetName>
		<exchangeRate>9.160148</exchangeRate>
		<inverseRate>0.109169</inverseRate>
		<inverseDescription>1 Salvadoran colon = 0.109169 Swiss Franc</inverseDescription>
	</item>
	<item>
		<title>1 CHF = 49.981718 GMD</title>
		<link>http://www.floatrates.com/chf/gmd/</link>
		<description>1 Swiss Franc = 49.981718 Gambian dalasi</description>
		<pubDate></pubDate>
		<baseCurrency>CHF</baseCurrency>
		<baseName>Swiss Franc</baseName>
		<targetCurrency>GMD</targetCurrency>
		<targetName>Gambian dalasi</targetName>
		<exchangeRate>49.981718</exchangeRate>
		<inverseRate>0.020007</inverseRate>
		<inverseDescription>1 Gambian dalasi = 0.020007 Swiss Franc</inverseDescription>
	</item>
	<item>
		<title>1 CHF = 52.455012 MKD</title>
		<link>http://www.floatrates.com/chf/mkd/</link>
		<description>1 Swiss Franc = 52.455012 Macedonian denar</description>
		<pubDate></pubDate>
		<baseCurrency>CHF</baseCurrency>
		<baseName>Swiss Franc</baseName>
		<targetCurrency>MKD</targetCurrency>
		<targetName>Macedonian denar</targetName>
		<exchangeRate>52.455012</exchangeRate>
		<inverseRate>0.019064</inverseRate>
		<inverseDescription>1 Macedonian denar = 0.019064 Swiss Franc</inverseDescription>
	</item>
	<item>
		<title>1 CHF = 120.279216 DZD</title>
		<link>http://www.floatrates.com/chf/dzd/</link>
		<description>1 Swiss Franc = 120.279216 Algerian Dinar</description>
		<pubDate></pubDate>
		<baseCurrency>CHF</baseCurrency>
		<baseName>Swiss Franc</baseName>
		<targetCurrency>DZD</targetCurrency>
		<targetName>Algerian Dinar</targetName>
		<exchangeRate>120.279216</exchangeRate>
		<inverseRate>0.008314</inverseRate>
		<inverseDescription>1 Algerian Dinar = 0.008314 Swiss Franc</inverseDescription>
	</item>
	<item>
		<title>1 CHF = 1,248.248085 IQD</title>
		<link>http://www.floatrates.com/chf/iqd/</link>
		<description>1 Swiss Franc = 1,248.248085 Iraqi dinar</description>
		<pubDate></pubDate>
		<baseCurrency>CHF</baseCurrency>
		<baseName>Swiss Franc</baseName>
		<targetCurrency>IQD</targetCurrency>
		<targetName>Iraqi dinar</targetName>
		<exchangeRate>1,248.248085</exchangeRate>
		<inverseRate>0.000801</inverseRate>
		<inverseDescription>1 Iraqi dinar = 0.000801 Swiss Franc</inverseDescription>
	</item>
	<item>
		<title>1 CHF = 0.745685 JOD</title>
		<link>http://www.floatrates.com/chf/jod/</link>
		<description>1 Swiss Franc = 0.745685 Jordanian Dinar</description>
		<pubDate></pubDate>
		<baseCurrency>CHF</baseCurrency>
		<baseName>Swiss Franc</baseName>
		<targetCurrency>JOD</targetCurrency>
		<targetName>Jordanian Dinar</targetName>
		<exchangeRate>0.745685</exchangeRate>
		<inverseRate>1.341049</inverseRate>
		<inverseDescription>1 Jordanian Dinar = 1.341049 Swiss Franc</inverseDescription>
	</item>
	<item>
		<title>1 CHF = 0.315829 KWD</title>
		<link>http://www.floatrates.com/chf/kwd/</link>
		<description>1 Swiss Franc = 0.315829 Kuwaiti Dinar</description>
		<pubDate></pubDate>
		<baseCurrency>CHF</baseCurrency>
		<baseName>Swiss Franc</baseName>
		<targetCurrency>KWD</targetCurrency>
		<targetName>Kuwaiti Dinar</targetName>
		<exchangeRate>0.315829</exchangeRate>
		<inverseRate>3.166274</inverseRate>
		<inverseDescription>1 Kuwaiti Dinar = 3.166274 Swiss Franc</inverseDescription>
	</item>
	<item>
		<title>1 CHF = 0.756879 LYD</title>
		<link>http://www.floatrates.com/chf/lyd/</link>
		<description>1 Swiss Franc = 0.756879 Libyan Dinar</description>
		<pubDate></pubDate>
		<baseCurrency>CHF</baseCurrency>
		<baseName>Swiss Franc</baseName>
		<targetCurrency>LYD</targetCurrency>
		<targetName>Libyan Dinar</targetName>
		<exchangeRate>0.756879</exchangeRate>
		<inverseRate>1.321215</inverseRate>
		<inverseDescription>1 Libyan Dinar = 1.321215 Swiss Franc</inverseDescription>
	</item>
	<item>
		<title>1 CHF = 101.183595 RSD</title>
		<link>http://www.floatrates.com/chf/rsd/</link>
		<description>1 Swiss Franc = 101.183595 Serbian Dinar</description>
		<pubDate></pubDate>
		<baseCurrency>CHF</baseCurrency>
		<baseName>Swiss Franc</baseName>
		<targetCurrency>RSD</targetCurrency>
		<targetName>Serbian Dinar</targetName>
		<exchangeRate>101.183595</exchangeRate>
		<inverseRate>0.009883</inverseRate>
		<inverseDescription>1 Serbian Dinar = 0.009883 Swiss Franc</inverseDescription>
	</item>
	<item>
		<title>1 CHF = 2.556540 TND</title>
		<link>http://www.floatrates.com/chf/tnd/</link>
		<description>1 Swiss Franc = 2.556540 Tunisian Dinar</description>
		<pubDate></pubDate>
		<baseCurrency>CHF</baseCurrency>
		<baseName>Swiss Franc</baseName>
		<targetCurrency>TND</targetCurrency>
		<targetName>Tunisian Dinar</targetName>
		<exchangeRate>2.556540</exchangeRate>
		<inverseRate>0.391154</inverseRate>
		<inverseDescription>1 Tunisian Dinar = 0.391154 Swiss Franc</inverseDescription>
	</item>
	<item>
		<title>1 CHF = 9.623644 MAD</title>
		<link>http://www.floatrates.com/chf/mad/</link>
		<description>1 Swiss Franc = 9.623644 Moroccan Dirham</description>
		<pubDate></pubDate>
		<baseCurrency>CHF</baseCurrency>
		<baseName>Swiss Franc</baseName>
		<targetCurrency>MAD</targetCurrency>
		<targetName>Moroccan Dirham</targetName>
		<exchangeRate>9.623644</exchangeRate>
		<inverseRate>0.103911</inverseRate>
		<inverseDescription>1 Moroccan Dirham = 0.103911 Swiss Franc</inverseDescription>
	</item>
	<item>
		<title>1 CHF = 21.408046 STN</title>
		<link>http://www.floatrates.com/chf/stn/</link>
		<description>1 Swiss Franc = 21.408046 São Tomé and Príncipe Dobra</description>
		<pubDate></pubDate>
		<baseCurrency>CHF</baseCurrency>
		<baseName>Swiss Franc</baseName>
		<targetCurrency>STN</targetCurrency>
		<targetName>São Tomé and Príncipe Dobra</targetName>
		<exchangeRate>21.408046</exchangeRate>
		<inverseRate>0.046711</inverseRate>
		<inverseDescription>1 São Tomé and Príncipe Dobra = 0.046711 Swiss Franc</inverseDescription>
	</item>
	<item>
		<title>1 CHF = 1.046109 BSD</title>
		<link>http://www.floatrates.com/chf/bsd/</link>
		<description>1 Swiss Franc = 1.046109 Bahamian Dollar</description>
		<pubDate></pubDate>
		<baseCurrency>CHF</baseCurrency>
		<baseName>Swiss Franc</baseName>
		<targetCurrency>BSD</targetCurrency>
		<targetName>Bahamian Dollar</targetName>
		<exchangeRate>1.046109</exchangeRate>
		<inverseRate>0.955924</inverseRate>
		<inverseDescription>1 Bahamian Dollar = 0.955924 Swiss Franc</inverseDescription>
	</item>
	<item>
		<title>1 CHF = 2.108593 BBD</title>
		<link>http://www.floatrates.com/chf/bbd/</link>
		<description>1 Swiss Franc = 2.108593 Barbadian Dollar</description>
		<pubDate></pubDate>
		<baseCurrency>CHF</baseCurrency>
		<baseName>Swiss Franc</baseName>
		<targetCurrency>BBD</targetCurrency>
		<targetName>Barbadian Dollar</targetName>
		<exchangeRate>2.108593</exchangeRate>
		<inverseRate>0.474250</inverseRate>
		<inverseDescription>1 Barbadian Dollar = 0.474250 Swiss Franc</inverseDescription>
	</item>
	<item>
		<title>1 CHF = 2.102932 BZD</title>
		<link>http://www.floatrates.com/chf/bzd/</link>
		<description>1 Swiss Franc = 2.102932 Belize dollar</description>
		<pubDate></pubDate>
		<baseCurrency>CHF</baseCurrency>
		<baseName>Swiss Franc</baseName>
		<targetCurrency>BZD</targetCurrency>
		<targetName>Belize dollar</targetName>
		<exchangeRate>2.102932</exchangeRate>
		<inverseRate>0.475527</inverseRate>
		<inverseDescription>1 Belize dollar = 0.475527 Swiss Franc</inverseDescription>
	</item>
	<item>
		<title>1 CHF = 1.384353 BND</title>
		<link>http://www.floatrates.com/chf/bnd/</link>
		<description>1 Swiss Franc = 1.384353 Brunei Dollar</description>
		<pubDate></pubDate>
		<baseCurrency>CHF</baseCurrency>
		<baseName>Swiss Franc</baseName>
		<targetCurrency>BND</targetCurrency>
		<targetName>Brunei Dollar</targetName>
		<exchangeRate>1.384353</exchangeRate>
		<inverseRate>0.722359</inverseRate>
		<inverseDescription>1 Brunei Dollar = 0.722359 Swiss Franc</inverseDescription>
	</item>
	<item>
		<title>1 CHF = 2.127821 FJD</title>
		<link>http://www.floatrates.com/chf/fjd/</link>
		<description>1 Swiss Franc = 2.127821 Fiji Dollar</description>
		<pubDate></pubDate>
		<baseCurrency>CHF</baseCurrency>
		<baseName>Swiss Franc</baseName>
		<targetCurrency>FJD</targetCurrency>
		<targetName>Fiji Dollar</targetName>
		<exchangeRate>2.127821</exchangeRate>
		<inverseRate>0.469964</inverseRate>
		<inverseDescription>1 Fiji Dollar = 0.469964 Swiss Franc</inverseDescription>
	</item>
	<item>
		<title>1 CHF = 216.634387 GYD</title>
		<link>http://www.floatrates.com/chf/gyd/</link>
		<description>1 Swiss Franc = 216.634387 Guyanese dollar</description>
		<pubDate></pubDate>
		<baseCurrency>CHF</baseCurrency>
		<baseName>Swiss Franc</baseName>
		<targetCurrency>GYD</targetCurrency>
		<targetName>Guyanese dollar</targetName>
		<exchangeRate>216.634387</exchangeRate>
		<inverseRate>0.004616</inverseRate>
		<inverseDescription>1 Guyanese dollar = 0.004616 Swiss Franc</inverseDescription>
	</item>
	<item>
		<title>1 CHF = 132.855816 JMD</title>
		<link>http://www.floatrates.com/chf/jmd/</link>
		<description>1 Swiss Franc = 132.855816 Jamaican Dollar</description>
		<pubDate></pubDate>
		<baseCurrency>CHF</baseCurrency>
		<baseName>Swiss Franc</baseName>
		<targetCurrency>JMD</targetCurrency>
		<targetName>Jamaican Dollar</targetName>
		<exchangeRate>132.855816</exchangeRate>
		<inverseRate>0.007527</inverseRate>
		<inverseDescription>1 Jamaican Dollar = 0.007527 Swiss Franc</inverseDescription>
	</item>
	<item>
		<title>1 CHF = 137.926649 LRD</title>
		<link>http://www.floatrates.com/chf/lrd/</link>
		<description>1 Swiss Franc = 137.926649 Liberian dollar</description>
		<pubDate></pubDate>
		<baseCurrency>CHF</baseCurrency>
		<baseName>Swiss Franc</baseName>
		<targetCurrency>LRD</targetCurrency>
		<targetName>Liberian dollar</targetName>
		<exchangeRate>137.926649</exchangeRate>
		<inverseRate>0.007250</inverseRate>
		<inverseDescription>1 Liberian dollar = 0.007250 Swiss Franc</inverseDescription>
	</item>
	<item>
		<title>1 CHF = 12.538786 NAD</title>
		<link>http://www.floatrates.com/chf/nad/</link>
		<description>1 Swiss Franc = 12.538786 Namibian dollar</description>
		<pubDate></pubDate>
		<baseCurrency>CHF</baseCurrency>
		<baseName>Swiss Franc</baseName>
		<targetCurrency>NAD</targetCurrency>
		<targetName>Namibian dollar</targetName>
		<exchangeRate>12.538786</exchangeRate>
		<inverseRate>0.079753</inverseRate>
		<inverseDescription>1 Namibian dollar = 0.079753 Swiss Franc</inverseDescription>
	</item>
	<item>
		<title>1 CHF = 7.820122 SRD</title>
		<link>http://www.floatrates.com/chf/srd/</link>
		<description>1 Swiss Franc = 7.820122 Surinamese dollar</description>
		<pubDate></pubDate>
		<baseCurrency>CHF</baseCurrency>
		<baseName>Swiss Franc</baseName>
		<targetCurrency>SRD</targetCurrency>
		<targetName>Surinamese dollar</targetName>
		<exchangeRate>7.820122</exchangeRate>
		<inverseRate>0.127875</inverseRate>
		<inverseDescription>1 Surinamese dollar = 0.127875 Swiss Franc</inverseDescription>
	</item>
	<item>
		<title>1 CHF = 7.132022 TTD</title>
		<link>http://www.floatrates.com/chf/ttd/</link>
		<description>1 Swiss Franc = 7.132022 Trinidad Tobago Dollar</description>
		<pubDate></pubDate>
		<baseCurrency>CHF</baseCurrency>
		<baseName>Swiss Franc</baseName>
		<targetCurrency>TTD</targetCurrency>
		<targetName>Trinidad Tobago Dollar</targetName>
		<exchangeRate>7.132022</exchangeRate>
		<inverseRate>0.140213</inverseRate>
		<inverseDescription>1 Trinidad Tobago Dollar = 0.140213 Swiss Franc</inverseDescription>
	</item>
	<item>
		<title>1 CHF = 2.836927 XCD</title>
		<link>http://www.floatrates.com/chf/xcd/</link>
		<description>1 Swiss Franc = 2.836927 East Caribbean Dollar</description>
		<pubDate></pubDate>
		<baseCurrency>CHF</baseCurrency>
		<baseName>Swiss Franc</baseName>
		<targetCurrency>XCD</targetCurrency>
		<targetName>East Caribbean Dollar</targetName>
		<exchangeRate>2.836927</exchangeRate>
		<inverseRate>0.352494</inverseRate>
		<inverseDescription>1 East Caribbean Dollar = 0.352494 Swiss Franc</inverseDescription>
	</item>
	<item>
		<title>1 CHF = 8.030396 SBD</title>
		<link>http://www.floatrates.com/chf/sbd/</link>
		<description>1 Swiss Franc = 8.030396 Solomon Islands dollar</description>
		<pubDate></pubDate>
		<baseCurrency>CHF</baseCurrency>
		<baseName>Swiss Franc</baseName>
		<targetCurrency>SBD</targetCurrency>
		<targetName>Solomon Islands dollar</targetName>
		<exchangeRate>8.030396</exchangeRate>
		<inverseRate>0.124527</inverseRate>
		<inverseDescription>1 Solomon Islands dollar = 0.124527 Swiss Franc</inverseDescription>
	</item>
	<item>
		<title>1 CHF = 504.365263 AMD</title>
		<link>http://www.floatrates.com/chf/amd/</link>
		<description>1 Swiss Franc = 504.365263 Armenia Dram</description>
		<pubDate></pubDate>
		<baseCurrency>CHF</baseCurrency>
		<baseName>Swiss Franc</baseName>
		<targetCurrency>AMD</targetCurrency>
		<targetName>Armenia Dram</targetName>
		<exchangeRate>504.365263</exchangeRate>
		<inverseRate>0.001983</inverseRate>
		<inverseDescription>1 Armenia Dram = 0.001983 Swiss Franc</inverseDescription>
	</item>
	<item>
		<title>1 CHF = 94.847197 CVE</title>
		<link>http://www.floatrates.com/chf/cve/</link>
		<description>1 Swiss Franc = 94.847197 Cape Verde escudo</description>
		<pubDate></pubDate>
		<baseCurrency>CHF</baseCurrency>
		<baseName>Swiss Franc</baseName>
		<targetCurrency>CVE</targetCurrency>
		<targetName>Cape Verde escudo</targetName>
		<exchangeRate>94.847197</exchangeRate>
		<inverseRate>0.010543</inverseRate>
		<inverseDescription>1 Cape Verde escudo = 0.010543 Swiss Franc</inverseDescription>
	</item>
	<item>
		<title>1 CHF = 1.867920 AWG</title>
		<link>http://www.floatrates.com/chf/awg/</link>
		<description>1 Swiss Franc = 1.867920 Aruban florin</description>
		<pubDate></pubDate>
		<baseCurrency>CHF</baseCurrency>
		<baseName>Swiss Franc</baseName>
		<targetCurrency>AWG</targetCurrency>
		<targetName>Aruban florin</targetName>
		<exchangeRate>1.867920</exchangeRate>
		<inverseRate>0.535355</inverseRate>
		<inverseDescription>1 Aruban florin = 0.535355 Swiss Franc</inverseDescription>
	</item>
	<item>
		<title>1 CHF = 1,841.833948 BIF</title>
		<link>http://www.floatrates.com/chf/bif/</link>
		<description>1 Swiss Franc = 1,841.833948 Burundian franc</description>
		<pubDate></pubDate>
		<baseCurrency>CHF</baseCurrency>
		<baseName>Swiss Franc</baseName>
		<targetCurrency>BIF</targetCurrency>
		<targetName>Burundian franc</targetName>
		<exchangeRate>1,841.833948</exchangeRate>
		<inverseRate>0.000543</inverseRate>
		<inverseDescription>1 Burundian franc = 0.000543 Swiss Franc</inverseDescription>
	</item>
	<item>
		<title>1 CHF = 561.868852 XOF</title>
		<link>http://www.floatrates.com/chf/xof/</link>
		<description>1 Swiss Franc = 561.868852 West African CFA Franc</description>
		<pubDate></pubDate>
		<baseCurrency>CHF</baseCurrency>
		<baseName>Swiss Franc</baseName>
		<targetCurrency>XOF</targetCurrency>
		<targetName>West African CFA Franc</targetName>
		<exchangeRate>561.868852</exchangeRate>
		<inverseRate>0.001780</inverseRate>
		<inverseDescription>1 West African CFA Franc = 0.001780 Swiss Franc</inverseDescription>
	</item>
	<item>
		<title>1 CHF = 561.868852 XAF</title>
		<link>http://www.floatrates.com/chf/xaf/</link>
		<description>1 Swiss Franc = 561.868852 Central African CFA Franc</description>
		<pubDate></pubDate>
		<baseCurrency>CHF</baseCurrency>
		<baseName>Swiss Franc</baseName>
		<targetCurrency>XAF</targetCurrency>
		<targetName>Central African CFA Franc</targetName>
		<exchangeRate>561.868852</exchangeRate>
		<inverseRate>0.001780</inverseRate>
		<inverseDescription>1 Central African CFA Franc = 0.001780 Swiss Franc</inverseDescription>
	</item>
	<item>
		<title>1 CHF = 101.682045 XPF</title>
		<link>http://www.floatrates.com/chf/xpf/</link>
		<description>1 Swiss Franc = 101.682045 CFP Franc</description>
		<pubDate></pubDate>
		<baseCurrency>CHF</baseCurrency>
		<baseName>Swiss Franc</baseName>
		<targetCurrency>XPF</targetCurrency>
		<targetName>CFP Franc</targetName>
		<exchangeRate>101.682045</exchangeRate>
		<inverseRate>0.009835</inverseRate>
		<inverseDescription>1 CFP Franc = 0.009835 Swiss Franc</inverseDescription>
	</item>
	<item>
		<title>1 CHF = 185.126957 DJF</title>
		<link>http://www.floatrates.com/chf/djf/</link>
		<description>1 Swiss Franc = 185.126957 Djiboutian franc</description>
		<pubDate></pubDate>
		<baseCurrency>CHF</baseCurrency>
		<baseName>Swiss Franc</baseName>
		<targetCurrency>DJF</targetCurrency>
		<targetName>Djiboutian franc</targetName>
		<exchangeRate>185.126957</exchangeRate>
		<inverseRate>0.005402</inverseRate>
		<inverseDescription>1 Djiboutian franc = 0.005402 Swiss Franc</inverseDescription>
	</item>
	<item>
		<title>1 CHF = 9,435.191138 GNF</title>
		<link>http://www.floatrates.com/chf/gnf/</link>
		<description>1 Swiss Franc = 9,435.191138 Guinean franc</description>
		<pubDate></pubDate>
		<baseCurrency>CHF</baseCurrency>
		<baseName>Swiss Franc</baseName>
		<targetCurrency>GNF</targetCurrency>
		<targetName>Guinean franc</targetName>
		<exchangeRate>9,435.191138</exchangeRate>
		<inverseRate>0.000106</inverseRate>
		<inverseDescription>1 Guinean franc = 0.000106 Swiss Franc</inverseDescription>
	</item>
	<item>
		<title>1 CHF = 418.685924 KMF</title>
		<link>http://www.floatrates.com/chf/kmf/</link>
		<description>1 Swiss Franc = 418.685924 	Comoro franc</description>
		<pubDate></pubDate>
		<baseCurrency>CHF</baseCurrency>
		<baseName>Swiss Franc</baseName>
		<targetCurrency>KMF</targetCurrency>
		<targetName>	Comoro franc</targetName>
		<exchangeRate>418.685924</exchangeRate>
		<inverseRate>0.002388</inverseRate>
		<inverseDescription>1 	Comoro franc = 0.002388 Swiss Franc</inverseDescription>
	</item>
	<item>
		<title>1 CHF = 1,697.359420 CDF</title>
		<link>http://www.floatrates.com/chf/cdf/</link>
		<description>1 Swiss Franc = 1,697.359420 Congolese franc</description>
		<pubDate></pubDate>
		<baseCurrency>CHF</baseCurrency>
		<baseName>Swiss Franc</baseName>
		<targetCurrency>CDF</targetCurrency>
		<targetName>Congolese franc</targetName>
		<exchangeRate>1,697.359420</exchangeRate>
		<inverseRate>0.000589</inverseRate>
		<inverseDescription>1 Congolese franc = 0.000589 Swiss Franc</inverseDescription>
	</item>
	<item>
		<title>1 CHF = 904.776717 RWF</title>
		<link>http://www.floatrates.com/chf/rwf/</link>
		<description>1 Swiss Franc = 904.776717 Rwandan franc</description>
		<pubDate></pubDate>
		<baseCurrency>CHF</baseCurrency>
		<baseName>Swiss Franc</baseName>
		<targetCurrency>RWF</targetCurrency>
		<targetName>Rwandan franc</targetName>
		<exchangeRate>904.776717</exchangeRate>
		<inverseRate>0.001105</inverseRate>
		<inverseDescription>1 Rwandan franc = 0.001105 Swiss Franc</inverseDescription>
	</item>
	<item>
		<title>1 CHF = 18.528078 EGP</title>
		<link>http://www.floatrates.com/chf/egp/</link>
		<description>1 Swiss Franc = 18.528078 Egyptian Pound</description>
		<pubDate></pubDate>
		<baseCurrency>CHF</baseCurrency>
		<baseName>Swiss Franc</baseName>
		<targetCurrency>EGP</targetCurrency>
		<targetName>Egyptian Pound</targetName>
		<exchangeRate>18.528078</exchangeRate>
		<inverseRate>0.053972</inverseRate>
		<inverseDescription>1 Egyptian Pound = 0.053972 Swiss Franc</inverseDescription>
	</item>
	<item>
		<title>1 CHF = 0.744106 GIP</title>
		<link>http://www.floatrates.com/chf/gip/</link>
		<description>1 Swiss Franc = 0.744106 Gibraltar pound</description>
		<pubDate></pubDate>
		<baseCurrency>CHF</baseCurrency>
		<baseName>Swiss Franc</baseName>
		<targetCurrency>GIP</targetCurrency>
		<targetName>Gibraltar pound</targetName>
		<exchangeRate>0.744106</exchangeRate>
		<inverseRate>1.343894</inverseRate>
		<inverseDescription>1 Gibraltar pound = 1.343894 Swiss Franc</inverseDescription>
	</item>
	<item>
		<title>1 CHF = 1,590.692290 LBP</title>
		<link>http://www.floatrates.com/chf/lbp/</link>
		<description>1 Swiss Franc = 1,590.692290 Lebanese Pound</description>
		<pubDate></pubDate>
		<baseCurrency>CHF</baseCurrency>
		<baseName>Swiss Franc</baseName>
		<targetCurrency>LBP</targetCurrency>
		<targetName>Lebanese Pound</targetName>
		<exchangeRate>1,590.692290</exchangeRate>
		<inverseRate>0.000629</inverseRate>
		<inverseDescription>1 Lebanese Pound = 0.000629 Swiss Franc</inverseDescription>
	</item>
	<item>
		<title>1 CHF = 138.609114 SSP</title>
		<link>http://www.floatrates.com/chf/ssp/</link>
		<description>1 Swiss Franc = 138.609114 South Sudanese pound</description>
		<pubDate></pubDate>
		<baseCurrency>CHF</baseCurrency>
		<baseName>Swiss Franc</baseName>
		<targetCurrency>SSP</targetCurrency>
		<targetName>South Sudanese pound</targetName>
		<exchangeRate>138.609114</exchangeRate>
		<inverseRate>0.007215</inverseRate>
		<inverseDescription>1 South Sudanese pound = 0.007215 Swiss Franc</inverseDescription>
	</item>
	<item>
		<title>1 CHF = 18.999360 SDG</title>
		<link>http://www.floatrates.com/chf/sdg/</link>
		<description>1 Swiss Franc = 18.999360 Sudanese pound</description>
		<pubDate></pubDate>
		<baseCurrency>CHF</baseCurrency>
		<baseName>Swiss Franc</baseName>
		<targetCurrency>SDG</targetCurrency>
		<targetName>Sudanese pound</targetName>
		<exchangeRate>18.999360</exchangeRate>
		<inverseRate>0.052633</inverseRate>
		<inverseDescription>1 Sudanese pound = 0.052633 Swiss Franc</inverseDescription>
	</item>
	<item>
		<title>1 CHF = 539.354956 SYP</title>
		<link>http://www.floatrates.com/chf/syp/</link>
		<description>1 Swiss Franc = 539.354956 Syrian pound</description>
		<pubDate></pubDate>
		<baseCurrency>CHF</baseCurrency>
		<baseName>Swiss Franc</baseName>
		<targetCurrency>SYP</targetCurrency>
		<targetName>Syrian pound</targetName>
		<exchangeRate>539.354956</exchangeRate>
		<inverseRate>0.001854</inverseRate>
		<inverseDescription>1 Syrian pound = 0.001854 Swiss Franc</inverseDescription>
	</item>
	<item>
		<title>1 CHF = 4.629360 GHS</title>
		<link>http://www.floatrates.com/chf/ghs/</link>
		<description>1 Swiss Franc = 4.629360 Ghanaian Cedi</description>
		<pubDate></pubDate>
		<baseCurrency>CHF</baseCurrency>
		<baseName>Swiss Franc</baseName>
		<targetCurrency>GHS</targetCurrency>
		<targetName>Ghanaian Cedi</targetName>
		<exchangeRate>4.629360</exchangeRate>
		<inverseRate>0.216013</inverseRate>
		<inverseDescription>1 Ghanaian Cedi = 0.216013 Swiss Franc</inverseDescription>
	</item>
	<item>
		<title>1 CHF = 67.798841 HTG</title>
		<link>http://www.floatrates.com/chf/htg/</link>
		<description>1 Swiss Franc = 67.798841 Haitian gourde</description>
		<pubDate></pubDate>
		<baseCurrency>CHF</baseCurrency>
		<baseName>Swiss Franc</baseName>
		<targetCurrency>HTG</targetCurrency>
		<targetName>Haitian gourde</targetName>
		<exchangeRate>67.798841</exchangeRate>
		<inverseRate>0.014750</inverseRate>
		<inverseDescription>1 Haitian gourde = 0.014750 Swiss Franc</inverseDescription>
	</item>
	<item>
		<title>1 CHF = 5,799.416621 PYG</title>
		<link>http://www.floatrates.com/chf/pyg/</link>
		<description>1 Swiss Franc = 5,799.416621 Paraguayan Guaraní</description>
		<pubDate></pubDate>
		<baseCurrency>CHF</baseCurrency>
		<baseName>Swiss Franc</baseName>
		<targetCurrency>PYG</targetCurrency>
		<targetName>Paraguayan Guaraní</targetName>
		<exchangeRate>5,799.416621</exchangeRate>
		<inverseRate>0.000172</inverseRate>
		<inverseDescription>1 Paraguayan Guaraní = 0.000172 Swiss Franc</inverseDescription>
	</item>
	<item>
		<title>1 CHF = 1.867534 ANG</title>
		<link>http://www.floatrates.com/chf/ang/</link>
		<description>1 Swiss Franc = 1.867534 Neth. Antillean Guilder</description>
		<pubDate></pubDate>
		<baseCurrency>CHF</baseCurrency>
		<baseName>Swiss Franc</baseName>
		<targetCurrency>ANG</targetCurrency>
		<targetName>Neth. Antillean Guilder</targetName>
		<exchangeRate>1.867534</exchangeRate>
		<inverseRate>0.535465</inverseRate>
		<inverseDescription>1 Neth. Antillean Guilder = 0.535465 Swiss Franc</inverseDescription>
	</item>
	<item>
		<title>1 CHF = 8,665.894978 LAK</title>
		<link>http://www.floatrates.com/chf/lak/</link>
		<description>1 Swiss Franc = 8,665.894978 Lao kip</description>
		<pubDate></pubDate>
		<baseCurrency>CHF</baseCurrency>
		<baseName>Swiss Franc</baseName>
		<targetCurrency>LAK</targetCurrency>
		<targetName>Lao kip</targetName>
		<exchangeRate>8,665.894978</exchangeRate>
		<inverseRate>0.000115</inverseRate>
		<inverseDescription>1 Lao kip = 0.000115 Swiss Franc</inverseDescription>
	</item>
	<item>
		<title>1 CHF = 759.176094 MWK</title>
		<link>http://www.floatrates.com/chf/mwk/</link>
		<description>1 Swiss Franc = 759.176094 Malawian kwacha</description>
		<pubDate></pubDate>
		<baseCurrency>CHF</baseCurrency>
		<baseName>Swiss Franc</baseName>
		<targetCurrency>MWK</targetCurrency>
		<targetName>Malawian kwacha</targetName>
		<exchangeRate>759.176094</exchangeRate>
		<inverseRate>0.001317</inverseRate>
		<inverseDescription>1 Malawian kwacha = 0.001317 Swiss Franc</inverseDescription>
	</item>
	<item>
		<title>1 CHF = 9.990816 ZMW</title>
		<link>http://www.floatrates.com/chf/zmw/</link>
		<description>1 Swiss Franc = 9.990816 Zambian kwacha</description>
		<pubDate></pubDate>
		<baseCurrency>CHF</baseCurrency>
		<baseName>Swiss Franc</baseName>
		<targetCurrency>ZMW</targetCurrency>
		<targetName>Zambian kwacha</targetName>
		<exchangeRate>9.990816</exchangeRate>
		<inverseRate>0.100092</inverseRate>
		<inverseDescription>1 Zambian kwacha = 0.100092 Swiss Franc</inverseDescription>
	</item>
	<item>
		<title>1 CHF = 225.854888 AOA</title>
		<link>http://www.floatrates.com/chf/aoa/</link>
		<description>1 Swiss Franc = 225.854888 Angolan kwanza</description>
		<pubDate></pubDate>
		<baseCurrency>CHF</baseCurrency>
		<baseName>Swiss Franc</baseName>
		<targetCurrency>AOA</targetCurrency>
		<targetName>Angolan kwanza</targetName>
		<exchangeRate>225.854888</exchangeRate>
		<inverseRate>0.004428</inverseRate>
		<inverseDescription>1 Angolan kwanza = 0.004428 Swiss Franc</inverseDescription>
	</item>
	<item>
		<title>1 CHF = 1,401.737085 MMK</title>
		<link>http://www.floatrates.com/chf/mmk/</link>
		<description>1 Swiss Franc = 1,401.737085 Myanma Kyat</description>
		<pubDate></pubDate>
		<baseCurrency>CHF</baseCurrency>
		<baseName>Swiss Franc</baseName>
		<targetCurrency>MMK</targetCurrency>
		<targetName>Myanma Kyat</targetName>
		<exchangeRate>1,401.737085</exchangeRate>
		<inverseRate>0.000713</inverseRate>
		<inverseDescription>1 Myanma Kyat = 0.000713 Swiss Franc</inverseDescription>
	</item>
	<item>
		<title>1 CHF = 2.546458 GEL</title>
		<link>http://www.floatrates.com/chf/gel/</link>
		<description>1 Swiss Franc = 2.546458 Georgian lari</description>
		<pubDate></pubDate>
		<baseCurrency>CHF</baseCurrency>
		<baseName>Swiss Franc</baseName>
		<targetCurrency>GEL</targetCurrency>
		<targetName>Georgian lari</targetName>
		<exchangeRate>2.546458</exchangeRate>
		<inverseRate>0.392702</inverseRate>
		<inverseDescription>1 Georgian lari = 0.392702 Swiss Franc</inverseDescription>
	</item>
	<item>
		<title>1 CHF = 17.406956 MDL</title>
		<link>http://www.floatrates.com/chf/mdl/</link>
		<description>1 Swiss Franc = 17.406956 Moldova Lei</description>
		<pubDate></pubDate>
		<baseCurrency>CHF</baseCurrency>
		<baseName>Swiss Franc</baseName>
		<targetCurrency>MDL</targetCurrency>
		<targetName>Moldova Lei</targetName>
		<exchangeRate>17.406956</exchangeRate>
		<inverseRate>0.057448</inverseRate>
		<inverseDescription>1 Moldova Lei = 0.057448 Swiss Franc</inverseDescription>
	</item>
	<item>
		<title>1 CHF = 110.798044 ALL</title>
		<link>http://www.floatrates.com/chf/all/</link>
		<description>1 Swiss Franc = 110.798044 Albanian lek</description>
		<pubDate></pubDate>
		<baseCurrency>CHF</baseCurrency>
		<baseName>Swiss Franc</baseName>
		<targetCurrency>ALL</targetCurrency>
		<targetName>Albanian lek</targetName>
		<exchangeRate>110.798044</exchangeRate>
		<inverseRate>0.009025</inverseRate>
		<inverseDescription>1 Albanian lek = 0.009025 Swiss Franc</inverseDescription>
	</item>
	<item>
		<title>1 CHF = 24.785173 HNL</title>
		<link>http://www.floatrates.com/chf/hnl/</link>
		<description>1 Swiss Franc = 24.785173 Honduran Lempira</description>
		<pubDate></pubDate>
		<baseCurrency>CHF</baseCurrency>
		<baseName>Swiss Franc</baseName>
		<targetCurrency>HNL</targetCurrency>
		<targetName>Honduran Lempira</targetName>
		<exchangeRate>24.785173</exchangeRate>
		<inverseRate>0.040347</inverseRate>
		<inverseDescription>1 Honduran Lempira = 0.040347 Swiss Franc</inverseDescription>
	</item>
	<item>
		<title>1 CHF = 8,157.287147 SLL</title>
		<link>http://www.floatrates.com/chf/sll/</link>
		<description>1 Swiss Franc = 8,157.287147 Sierra Leonean leone</description>
		<pubDate></pubDate>
		<baseCurrency>CHF</baseCurrency>
		<baseName>Swiss Franc</baseName>
		<targetCurrency>SLL</targetCurrency>
		<targetName>Sierra Leonean leone</targetName>
		<exchangeRate>8,157.287147</exchangeRate>
		<inverseRate>0.000123</inverseRate>
		<inverseDescription>1 Sierra Leonean leone = 0.000123 Swiss Franc</inverseDescription>
	</item>
	<item>
		<title>1 CHF = 12.538786 SZL</title>
		<link>http://www.floatrates.com/chf/szl/</link>
		<description>1 Swiss Franc = 12.538786 Swazi lilangeni</description>
		<pubDate></pubDate>
		<baseCurrency>CHF</baseCurrency>
		<baseName>Swiss Franc</baseName>
		<targetCurrency>SZL</targetCurrency>
		<targetName>Swazi lilangeni</targetName>
		<exchangeRate>12.538786</exchangeRate>
		<inverseRate>0.079753</inverseRate>
		<inverseDescription>1 Swazi lilangeni = 0.079753 Swiss Franc</inverseDescription>
	</item>
	<item>
		<title>1 CHF = 12.534437 LSL</title>
		<link>http://www.floatrates.com/chf/lsl/</link>
		<description>1 Swiss Franc = 12.534437 Lesotho loti</description>
		<pubDate></pubDate>
		<baseCurrency>CHF</baseCurrency>
		<baseName>Swiss Franc</baseName>
		<targetCurrency>LSL</targetCurrency>
		<targetName>Lesotho loti</targetName>
		<exchangeRate>12.534437</exchangeRate>
		<inverseRate>0.079780</inverseRate>
		<inverseDescription>1 Lesotho loti = 0.079780 Swiss Franc</inverseDescription>
	</item>
	<item>
		<title>1 CHF = 1.788415 AZN</title>
		<link>http://www.floatrates.com/chf/azn/</link>
		<description>1 Swiss Franc = 1.788415 Azerbaijan Manat</description>
		<pubDate></pubDate>
		<baseCurrency>CHF</baseCurrency>
		<baseName>Swiss Franc</baseName>
		<targetCurrency>AZN</targetCurrency>
		<targetName>Azerbaijan Manat</targetName>
		<exchangeRate>1.788415</exchangeRate>
		<inverseRate>0.559154</inverseRate>
		<inverseDescription>1 Azerbaijan Manat = 0.559154 Swiss Franc</inverseDescription>
	</item>
	<item>
		<title>1 CHF = 64.761258 MZN</title>
		<link>http://www.floatrates.com/chf/mzn/</link>
		<description>1 Swiss Franc = 64.761258 Mozambican metical</description>
		<pubDate></pubDate>
		<baseCurrency>CHF</baseCurrency>
		<baseName>Swiss Franc</baseName>
		<targetCurrency>MZN</targetCurrency>
		<targetName>Mozambican metical</targetName>
		<exchangeRate>64.761258</exchangeRate>
		<inverseRate>0.015441</inverseRate>
		<inverseDescription>1 Mozambican metical = 0.015441 Swiss Franc</inverseDescription>
	</item>
	<item>
		<title>1 CHF = 320.293311 NGN</title>
		<link>http://www.floatrates.com/chf/ngn/</link>
		<description>1 Swiss Franc = 320.293311 Nigerian Naira</description>
		<pubDate></pubDate>
		<baseCurrency>CHF</baseCurrency>
		<baseName>Swiss Franc</baseName>
		<targetCurrency>NGN</targetCurrency>
		<targetName>Nigerian Naira</targetName>
		<exchangeRate>320.293311</exchangeRate>
		<inverseRate>0.003122</inverseRate>
		<inverseDescription>1 Nigerian Naira = 0.003122 Swiss Franc</inverseDescription>
	</item>
	<item>
		<title>1 CHF = 15.773366 ERN</title>
		<link>http://www.floatrates.com/chf/ern/</link>
		<description>1 Swiss Franc = 15.773366 Eritrean nakfa</description>
		<pubDate></pubDate>
		<baseCurrency>CHF</baseCurrency>
		<baseName>Swiss Franc</baseName>
		<targetCurrency>ERN</targetCurrency>
		<targetName>Eritrean nakfa</targetName>
		<exchangeRate>15.773366</exchangeRate>
		<inverseRate>0.063398</inverseRate>
		<inverseDescription>1 Eritrean nakfa = 0.063398 Swiss Franc</inverseDescription>
	</item>
	<item>
		<title>1 CHF = 3.672536 TMT</title>
		<link>http://www.floatrates.com/chf/tmt/</link>
		<description>1 Swiss Franc = 3.672536 New Turkmenistan Manat</description>
		<pubDate></pubDate>
		<baseCurrency>CHF</baseCurrency>
		<baseName>Swiss Franc</baseName>
		<targetCurrency>TMT</targetCurrency>
		<targetName>New Turkmenistan Manat</targetName>
		<exchangeRate>3.672536</exchangeRate>
		<inverseRate>0.272291</inverseRate>
		<inverseDescription>1 New Turkmenistan Manat = 0.272291 Swiss Franc</inverseDescription>
	</item>
	<item>
		<title>1 CHF = 36.874267 MRU</title>
		<link>http://www.floatrates.com/chf/mru/</link>
		<description>1 Swiss Franc = 36.874267 Mauritanian ouguiya</description>
		<pubDate></pubDate>
		<baseCurrency>CHF</baseCurrency>
		<baseName>Swiss Franc</baseName>
		<targetCurrency>MRU</targetCurrency>
		<targetName>Mauritanian ouguiya</targetName>
		<exchangeRate>36.874267</exchangeRate>
		<inverseRate>0.027119</inverseRate>
		<inverseDescription>1 Mauritanian ouguiya = 0.027119 Swiss Franc</inverseDescription>
	</item>
	<item>
		<title>1 CHF = 2.283236 TOP</title>
		<link>http://www.floatrates.com/chf/top/</link>
		<description>1 Swiss Franc = 2.283236 Tongan paʻanga</description>
		<pubDate></pubDate>
		<baseCurrency>CHF</baseCurrency>
		<baseName>Swiss Franc</baseName>
		<targetCurrency>TOP</targetCurrency>
		<targetName>Tongan paʻanga</targetName>
		<exchangeRate>2.283236</exchangeRate>
		<inverseRate>0.437975</inverseRate>
		<inverseDescription>1 Tongan paʻanga = 0.437975 Swiss Franc</inverseDescription>
	</item>
	<item>
		<title>1 CHF = 8.458985 MOP</title>
		<link>http://www.floatrates.com/chf/mop/</link>
		<description>1 Swiss Franc = 8.458985 Macanese pataca</description>
		<pubDate></pubDate>
		<baseCurrency>CHF</baseCurrency>
		<baseName>Swiss Franc</baseName>
		<targetCurrency>MOP</targetCurrency>
		<targetName>Macanese pataca</targetName>
		<exchangeRate>8.458985</exchangeRate>
		<inverseRate>0.118217</inverseRate>
		<inverseDescription>1 Macanese pataca = 0.118217 Swiss Franc</inverseDescription>
	</item>
	<item>
		<title>1 CHF = 21.195674 ARS</title>
		<link>http://www.floatrates.com/chf/ars/</link>
		<description>1 Swiss Franc = 21.195674 Argentine Peso</description>
		<pubDate></pubDate>
		<baseCurrency>CHF</baseCurrency>
		<baseName>Swiss Franc</baseName>
		<targetCurrency>ARS</targetCurrency>
		<targetName>Argentine Peso</targetName>
		<exchangeRate>21.195674</exchangeRate>
		<inverseRate>0.047179</inverseRate>
		<inverseDescription>1 Argentine Peso = 0.047179 Swiss Franc</inverseDescription>
	</item>
	<item>
		<title>1 CHF = 51.849705 DOP</title>
		<link>http://www.floatrates.com/chf/dop/</link>
		<description>1 Swiss Franc = 51.849705 Dominican Peso</description>
		<pubDate></pubDate>
		<baseCurrency>CHF</baseCurrency>
		<baseName>Swiss Franc</baseName>
		<targetCurrency>DOP</targetCurrency>
		<targetName>Dominican Peso</targetName>
		<exchangeRate>51.849705</exchangeRate>
		<inverseRate>0.019287</inverseRate>
		<inverseDescription>1 Dominican Peso = 0.019287 Swiss Franc</inverseDescription>
	</item>
	<item>
		<title>1 CHF = 3,006.415763 COP</title>
		<link>http://www.floatrates.com/chf/cop/</link>
		<description>1 Swiss Franc = 3,006.415763 Colombian Peso</description>
		<pubDate></pubDate>
		<baseCurrency>CHF</baseCurrency>
		<baseName>Swiss Franc</baseName>
		<targetCurrency>COP</targetCurrency>
		<targetName>Colombian Peso</targetName>
		<exchangeRate>3,006.415763</exchangeRate>
		<inverseRate>0.000333</inverseRate>
		<inverseDescription>1 Colombian Peso = 0.000333 Swiss Franc</inverseDescription>
	</item>
	<item>
		<title>1 CHF = 1.046109 CUP</title>
		<link>http://www.floatrates.com/chf/cup/</link>
		<description>1 Swiss Franc = 1.046109 Cuban peso</description>
		<pubDate></pubDate>
		<baseCurrency>CHF</baseCurrency>
		<baseName>Swiss Franc</baseName>
		<targetCurrency>CUP</targetCurrency>
		<targetName>Cuban peso</targetName>
		<exchangeRate>1.046109</exchangeRate>
		<inverseRate>0.955924</inverseRate>
		<inverseDescription>1 Cuban peso = 0.955924 Swiss Franc</inverseDescription>
	</item>
	<item>
		<title>1 CHF = 29.804187 UYU</title>
		<link>http://www.floatrates.com/chf/uyu/</link>
		<description>1 Swiss Franc = 29.804187 Uruguayan Peso</description>
		<pubDate></pubDate>
		<baseCurrency>CHF</baseCurrency>
		<baseName>Swiss Franc</baseName>
		<targetCurrency>UYU</targetCurrency>
		<targetName>Uruguayan Peso</targetName>
		<exchangeRate>29.804187</exchangeRate>
		<inverseRate>0.033552</inverseRate>
		<inverseDescription>1 Uruguayan Peso = 0.033552 Swiss Franc</inverseDescription>
	</item>
	<item>
		<title>1 CHF = 10.072795 BWP</title>
		<link>http://www.floatrates.com/chf/bwp/</link>
		<description>1 Swiss Franc = 10.072795 Botswana Pula</description>
		<pubDate></pubDate>
		<baseCurrency>CHF</baseCurrency>
		<baseName>Swiss Franc</baseName>
		<targetCurrency>BWP</targetCurrency>
		<targetName>Botswana Pula</targetName>
		<exchangeRate>10.072795</exchangeRate>
		<inverseRate>0.099277</inverseRate>
		<inverseDescription>1 Botswana Pula = 0.099277 Swiss Franc</inverseDescription>
	</item>
	<item>
		<title>1 CHF = 7.758004 GTQ</title>
		<link>http://www.floatrates.com/chf/gtq/</link>
		<description>1 Swiss Franc = 7.758004 Guatemalan Quetzal</description>
		<pubDate></pubDate>
		<baseCurrency>CHF</baseCurrency>
		<baseName>Swiss Franc</baseName>
		<targetCurrency>GTQ</targetCurrency>
		<targetName>Guatemalan Quetzal</targetName>
		<exchangeRate>7.758004</exchangeRate>
		<inverseRate>0.128899</inverseRate>
		<inverseDescription>1 Guatemalan Quetzal = 0.128899 Swiss Franc</inverseDescription>
	</item>
	<item>
		<title>1 CHF = 39,513.662479 IRR</title>
		<link>http://www.floatrates.com/chf/irr/</link>
		<description>1 Swiss Franc = 39,513.662479 Iranian rial</description>
		<pubDate></pubDate>
		<baseCurrency>CHF</baseCurrency>
		<baseName>Swiss Franc</baseName>
		<targetCurrency>IRR</targetCurrency>
		<targetName>Iranian rial</targetName>
		<exchangeRate>39,513.662479</exchangeRate>
		<inverseRate>0.000025</inverseRate>
		<inverseDescription>1 Iranian rial = 0.000025 Swiss Franc</inverseDescription>
	</item>
	<item>
		<title>1 CHF = 261.671123 YER</title>
		<link>http://www.floatrates.com/chf/yer/</link>
		<description>1 Swiss Franc = 261.671123 Yemeni rial</description>
		<pubDate></pubDate>
		<baseCurrency>CHF</baseCurrency>
		<baseName>Swiss Franc</baseName>
		<targetCurrency>YER</targetCurrency>
		<targetName>Yemeni rial</targetName>
		<exchangeRate>261.671123</exchangeRate>
		<inverseRate>0.003822</inverseRate>
		<inverseDescription>1 Yemeni rial = 0.003822 Swiss Franc</inverseDescription>
	</item>
	<item>
		<title>1 CHF = 3.838705 QAR</title>
		<link>http://www.floatrates.com/chf/qar/</link>
		<description>1 Swiss Franc = 3.838705 Qatari Rial</description>
		<pubDate></pubDate>
		<baseCurrency>CHF</baseCurrency>
		<baseName>Swiss Franc</baseName>
		<targetCurrency>QAR</targetCurrency>
		<targetName>Qatari Rial</targetName>
		<exchangeRate>3.838705</exchangeRate>
		<inverseRate>0.260505</inverseRate>
		<inverseDescription>1 Qatari Rial = 0.260505 Swiss Franc</inverseDescription>
	</item>
	<item>
		<title>1 CHF = 0.405476 OMR</title>
		<link>http://www.floatrates.com/chf/omr/</link>
		<description>1 Swiss Franc = 0.405476 Omani Rial</description>
		<pubDate></pubDate>
		<baseCurrency>CHF</baseCurrency>
		<baseName>Swiss Franc</baseName>
		<targetCurrency>OMR</targetCurrency>
		<targetName>Omani Rial</targetName>
		<exchangeRate>0.405476</exchangeRate>
		<inverseRate>2.466237</inverseRate>
		<inverseDescription>1 Omani Rial = 2.466237 Swiss Franc</inverseDescription>
	</item>
	<item>
		<title>1 CHF = 3.954257 SAR</title>
		<link>http://www.floatrates.com/chf/sar/</link>
		<description>1 Swiss Franc = 3.954257 Saudi Riyal</description>
		<pubDate></pubDate>
		<baseCurrency>CHF</baseCurrency>
		<baseName>Swiss Franc</baseName>
		<targetCurrency>SAR</targetCurrency>
		<targetName>Saudi Riyal</targetName>
		<exchangeRate>3.954257</exchangeRate>
		<inverseRate>0.252892</inverseRate>
		<inverseDescription>1 Saudi Riyal = 0.252892 Swiss Franc</inverseDescription>
	</item>
	<item>
		<title>1 CHF = 4,177.662666 KHR</title>
		<link>http://www.floatrates.com/chf/khr/</link>
		<description>1 Swiss Franc = 4,177.662666 Cambodian riel</description>
		<pubDate></pubDate>
		<baseCurrency>CHF</baseCurrency>
		<baseName>Swiss Franc</baseName>
		<targetCurrency>KHR</targetCurrency>
		<targetName>Cambodian riel</targetName>
		<exchangeRate>4,177.662666</exchangeRate>
		<inverseRate>0.000239</inverseRate>
		<inverseDescription>1 Cambodian riel = 0.000239 Swiss Franc</inverseDescription>
	</item>
	<item>
		<title>1 CHF = 2.055630 BYN</title>
		<link>http://www.floatrates.com/chf/byn/</link>
		<description>1 Swiss Franc = 2.055630 Belarussian Ruble</description>
		<pubDate></pubDate>
		<baseCurrency>CHF</baseCurrency>
		<baseName>Swiss Franc</baseName>
		<targetCurrency>BYN</targetCurrency>
		<targetName>Belarussian Ruble</targetName>
		<exchangeRate>2.055630</exchangeRate>
		<inverseRate>0.486469</inverseRate>
		<inverseDescription>1 Belarussian Ruble = 0.486469 Swiss Franc</inverseDescription>
	</item>
	<item>
		<title>1 CHF = 164.413338 LKR</title>
		<link>http://www.floatrates.com/chf/lkr/</link>
		<description>1 Swiss Franc = 164.413338 Sri Lanka Rupee</description>
		<pubDate></pubDate>
		<baseCurrency>CHF</baseCurrency>
		<baseName>Swiss Franc</baseName>
		<targetCurrency>LKR</targetCurrency>
		<targetName>Sri Lanka Rupee</targetName>
		<exchangeRate>164.413338</exchangeRate>
		<inverseRate>0.006082</inverseRate>
		<inverseDescription>1 Sri Lanka Rupee = 0.006082 Swiss Franc</inverseDescription>
	</item>
	<item>
		<title>1 CHF = 16.175820 MVR</title>
		<link>http://www.floatrates.com/chf/mvr/</link>
		<description>1 Swiss Franc = 16.175820 Maldivian rufiyaa</description>
		<pubDate></pubDate>
		<baseCurrency>CHF</baseCurrency>
		<baseName>Swiss Franc</baseName>
		<targetCurrency>MVR</targetCurrency>
		<targetName>Maldivian rufiyaa</targetName>
		<exchangeRate>16.175820</exchangeRate>
		<inverseRate>0.061821</inverseRate>
		<inverseDescription>1 Maldivian rufiyaa = 0.061821 Swiss Franc</inverseDescription>
	</item>
	<item>
		<title>1 CHF = 34.833553 MUR</title>
		<link>http://www.floatrates.com/chf/mur/</link>
		<description>1 Swiss Franc = 34.833553 Mauritian Rupee</description>
		<pubDate></pubDate>
		<baseCurrency>CHF</baseCurrency>
		<baseName>Swiss Franc</baseName>
		<targetCurrency>MUR</targetCurrency>
		<targetName>Mauritian Rupee</targetName>
		<exchangeRate>34.833553</exchangeRate>
		<inverseRate>0.028708</inverseRate>
		<inverseDescription>1 Mauritian Rupee = 0.028708 Swiss Franc</inverseDescription>
	</item>
	<item>
		<title>1 CHF = 110.001918 NPR</title>
		<link>http://www.floatrates.com/chf/npr/</link>
		<description>1 Swiss Franc = 110.001918 Nepalese Rupee</description>
		<pubDate></pubDate>
		<baseCurrency>CHF</baseCurrency>
		<baseName>Swiss Franc</baseName>
		<targetCurrency>NPR</targetCurrency>
		<targetName>Nepalese Rupee</targetName>
		<exchangeRate>110.001918</exchangeRate>
		<inverseRate>0.009091</inverseRate>
		<inverseDescription>1 Nepalese Rupee = 0.009091 Swiss Franc</inverseDescription>
	</item>
	<item>
		<title>1 CHF = 121.685144 PKR</title>
		<link>http://www.floatrates.com/chf/pkr/</link>
		<description>1 Swiss Franc = 121.685144 Pakistani Rupee</description>
		<pubDate></pubDate>
		<baseCurrency>CHF</baseCurrency>
		<baseName>Swiss Franc</baseName>
		<targetCurrency>PKR</targetCurrency>
		<targetName>Pakistani Rupee</targetName>
		<exchangeRate>121.685144</exchangeRate>
		<inverseRate>0.008218</inverseRate>
		<inverseDescription>1 Pakistani Rupee = 0.008218 Swiss Franc</inverseDescription>
	</item>
	<item>
		<title>1 CHF = 14.077437 SCR</title>
		<link>http://www.floatrates.com/chf/scr/</link>
		<description>1 Swiss Franc = 14.077437 Seychelles rupee</description>
		<pubDate></pubDate>
		<baseCurrency>CHF</baseCurrency>
		<baseName>Swiss Franc</baseName>
		<targetCurrency>SCR</targetCurrency>
		<targetName>Seychelles rupee</targetName>
		<exchangeRate>14.077437</exchangeRate>
		<inverseRate>0.071036</inverseRate>
		<inverseDescription>1 Seychelles rupee = 0.071036 Swiss Franc</inverseDescription>
	</item>
	<item>
		<title>1 CHF = 3.418622 PEN</title>
		<link>http://www.floatrates.com/chf/pen/</link>
		<description>1 Swiss Franc = 3.418622 Peruvian Nuevo Sol</description>
		<pubDate></pubDate>
		<baseCurrency>CHF</baseCurrency>
		<baseName>Swiss Franc</baseName>
		<targetCurrency>PEN</targetCurrency>
		<targetName>Peruvian Nuevo Sol</targetName>
		<exchangeRate>3.418622</exchangeRate>
		<inverseRate>0.292516</inverseRate>
		<inverseDescription>1 Peruvian Nuevo Sol = 0.292516 Swiss Franc</inverseDescription>
	</item>
	<item>
		<title>1 CHF = 71.723261 KGS</title>
		<link>http://www.floatrates.com/chf/kgs/</link>
		<description>1 Swiss Franc = 71.723261 Kyrgyzstan Som</description>
		<pubDate></pubDate>
		<baseCurrency>CHF</baseCurrency>
		<baseName>Swiss Franc</baseName>
		<targetCurrency>KGS</targetCurrency>
		<targetName>Kyrgyzstan Som</targetName>
		<exchangeRate>71.723261</exchangeRate>
		<inverseRate>0.013942</inverseRate>
		<inverseDescription>1 Kyrgyzstan Som = 0.013942 Swiss Franc</inverseDescription>
	</item>
	<item>
		<title>1 CHF = 9.271784 TJS</title>
		<link>http://www.floatrates.com/chf/tjs/</link>
		<description>1 Swiss Franc = 9.271784 Tajikistan Ruble</description>
		<pubDate></pubDate>
		<baseCurrency>CHF</baseCurrency>
		<baseName>Swiss Franc</baseName>
		<targetCurrency>TJS</targetCurrency>
		<targetName>Tajikistan Ruble</targetName>
		<exchangeRate>9.271784</exchangeRate>
		<inverseRate>0.107854</inverseRate>
		<inverseDescription>1 Tajikistan Ruble = 0.107854 Swiss Franc</inverseDescription>
	</item>
	<item>
		<title>1 CHF = 8,553.893550 UZS</title>
		<link>http://www.floatrates.com/chf/uzs/</link>
		<description>1 Swiss Franc = 8,553.893550 Uzbekistan Sum</description>
		<pubDate></pubDate>
		<baseCurrency>CHF</baseCurrency>
		<baseName>Swiss Franc</baseName>
		<targetCurrency>UZS</targetCurrency>
		<targetName>Uzbekistan Sum</targetName>
		<exchangeRate>8,553.893550</exchangeRate>
		<inverseRate>0.000117</inverseRate>
		<inverseDescription>1 Uzbekistan Sum = 0.000117 Swiss Franc</inverseDescription>
	</item>
	<item>
		<title>1 CHF = 105.771351 KES</title>
		<link>http://www.floatrates.com/chf/kes/</link>
		<description>1 Swiss Franc = 105.771351 Kenyan shilling</description>
		<pubDate></pubDate>
		<baseCurrency>CHF</baseCurrency>
		<baseName>Swiss Franc</baseName>
		<targetCurrency>KES</targetCurrency>
		<targetName>Kenyan shilling</targetName>
		<exchangeRate>105.771351</exchangeRate>
		<inverseRate>0.009454</inverseRate>
		<inverseDescription>1 Kenyan shilling = 0.009454 Swiss Franc</inverseDescription>
	</item>
	<item>
		<title>1 CHF = 605.204858 SOS</title>
		<link>http://www.floatrates.com/chf/sos/</link>
		<description>1 Swiss Franc = 605.204858 Somali shilling</description>
		<pubDate></pubDate>
		<baseCurrency>CHF</baseCurrency>
		<baseName>Swiss Franc</baseName>
		<targetCurrency>SOS</targetCurrency>
		<targetName>Somali shilling</targetName>
		<exchangeRate>605.204858</exchangeRate>
		<inverseRate>0.001652</inverseRate>
		<inverseDescription>1 Somali shilling = 0.001652 Swiss Franc</inverseDescription>
	</item>
	<item>
		<title>1 CHF = 2,366.521418 TZS</title>
		<link>http://www.floatrates.com/chf/tzs/</link>
		<description>1 Swiss Franc = 2,366.521418 Tanzanian shilling</description>
		<pubDate></pubDate>
		<baseCurrency>CHF</baseCurrency>
		<baseName>Swiss Franc</baseName>
		<targetCurrency>TZS</targetCurrency>
		<targetName>Tanzanian shilling</targetName>
		<exchangeRate>2,366.521418</exchangeRate>
		<inverseRate>0.000423</inverseRate>
		<inverseDescription>1 Tanzanian shilling = 0.000423 Swiss Franc</inverseDescription>
	</item>
	<item>
		<title>1 CHF = 3,832.108384 UGX</title>
		<link>http://www.floatrates.com/chf/ugx/</link>
		<description>1 Swiss Franc = 3,832.108384 Ugandan shilling</description>
		<pubDate></pubDate>
		<baseCurrency>CHF</baseCurrency>
		<baseName>Swiss Franc</baseName>
		<targetCurrency>UGX</targetCurrency>
		<targetName>Ugandan shilling</targetName>
		<exchangeRate>3,832.108384</exchangeRate>
		<inverseRate>0.000261</inverseRate>
		<inverseDescription>1 Ugandan shilling = 0.000261 Swiss Franc</inverseDescription>
	</item>
	<item>
		<title>1 CHF = 87.047297 BDT</title>
		<link>http://www.floatrates.com/chf/bdt/</link>
		<description>1 Swiss Franc = 87.047297 Bangladeshi taka</description>
		<pubDate></pubDate>
		<baseCurrency>CHF</baseCurrency>
		<baseName>Swiss Franc</baseName>
		<targetCurrency>BDT</targetCurrency>
		<targetName>Bangladeshi taka</targetName>
		<exchangeRate>87.047297</exchangeRate>
		<inverseRate>0.011488</inverseRate>
		<inverseDescription>1 Bangladeshi taka = 0.011488 Swiss Franc</inverseDescription>
	</item>
	<item>
		<title>1 CHF = 2.619746 WST</title>
		<link>http://www.floatrates.com/chf/wst/</link>
		<description>1 Swiss Franc = 2.619746 Samoan tala</description>
		<pubDate></pubDate>
		<baseCurrency>CHF</baseCurrency>
		<baseName>Swiss Franc</baseName>
		<targetCurrency>WST</targetCurrency>
		<targetName>Samoan tala</targetName>
		<exchangeRate>2.619746</exchangeRate>
		<inverseRate>0.381716</inverseRate>
		<inverseDescription>1 Samoan tala = 0.381716 Swiss Franc</inverseDescription>
	</item>
	<item>
		<title>1 CHF = 337.799997 KZT</title>
		<link>http://www.floatrates.com/chf/kzt/</link>
		<description>1 Swiss Franc = 337.799997 Kazakhstani Tenge</description>
		<pubDate></pubDate>
		<baseCurrency>CHF</baseCurrency>
		<baseName>Swiss Franc</baseName>
		<targetCurrency>KZT</targetCurrency>
		<targetName>Kazakhstani Tenge</targetName>
		<exchangeRate>337.799997</exchangeRate>
		<inverseRate>0.002960</inverseRate>
		<inverseDescription>1 Kazakhstani Tenge = 0.002960 Swiss Franc</inverseDescription>
	</item>
	<item>
		<title>1 CHF = 2,507.757256 MNT</title>
		<link>http://www.floatrates.com/chf/mnt/</link>
		<description>1 Swiss Franc = 2,507.757256 Mongolian togrog</description>
		<pubDate></pubDate>
		<baseCurrency>CHF</baseCurrency>
		<baseName>Swiss Franc</baseName>
		<targetCurrency>MNT</targetCurrency>
		<targetName>Mongolian togrog</targetName>
		<exchangeRate>2,507.757256</exchangeRate>
		<inverseRate>0.000399</inverseRate>
		<inverseDescription>1 Mongolian togrog = 0.000399 Swiss Franc</inverseDescription>
	</item>
	<item>
		<title>1 CHF = 113.978180 VUV</title>
		<link>http://www.floatrates.com/chf/vuv/</link>
		<description>1 Swiss Franc = 113.978180 Vanuatu vatu</description>
		<pubDate></pubDate>
		<baseCurrency>CHF</baseCurrency>
		<baseName>Swiss Franc</baseName>
		<targetCurrency>VUV</targetCurrency>
		<targetName>Vanuatu vatu</targetName>
		<exchangeRate>113.978180</exchangeRate>
		<inverseRate>0.008774</inverseRate>
		<inverseDescription>1 Vanuatu vatu = 0.008774 Swiss Franc</inverseDescription>
	</item>
	<item>
		<title>1 CHF = 1.666288 BAM</title>
		<link>http://www.floatrates.com/chf/bam/</link>
		<description>1 Swiss Franc = 1.666288 Bosnia and Herzegovina convertible mark</description>
		<pubDate></pubDate>
		<baseCurrency>CHF</baseCurrency>
		<baseName>Swiss Franc</baseName>
		<targetCurrency>BAM</targetCurrency>
		<targetName>Bosnia and Herzegovina convertible mark</targetName>
		<exchangeRate>1.666288</exchangeRate>
		<inverseRate>0.600136</inverseRate>
		<inverseDescription>1 Bosnia and Herzegovina convertible mark = 0.600136 Swiss Franc</inverseDescription>
	</item>
	<item>
		<title>1 CHF = 3.613966 PLN</title>
		<link>http://www.floatrates.com/chf/pln/</link>
		<description>1 Swiss Franc = 3.613966 Polish Zloty</description>
		<pubDate></pubDate>
		<baseCurrency>CHF</baseCurrency>
		<baseName>Swiss Franc</baseName>
		<targetCurrency>PLN</targetCurrency>
		<targetName>Polish Zloty</targetName>
		<exchangeRate>3.613966</exchangeRate>
		<inverseRate>0.276704</inverseRate>
		<inverseDescription>1 Polish Zloty = 0.276704 Swiss Franc</inverseDescription>
	</item>
	<item>
		<title>1 CHF = 37.286887 MRO</title>
		<link>http://www.floatrates.com/chf/mro/</link>
		<description>1 Swiss Franc = 37.286887 Mauritanian Ouguiya</description>
		<pubDate></pubDate>
		<baseCurrency>CHF</baseCurrency>
		<baseName>Swiss Franc</baseName>
		<targetCurrency>MRO</targetCurrency>
		<targetName>Mauritanian Ouguiya</targetName>
		<exchangeRate>37.286887</exchangeRate>
		<inverseRate>0.026819</inverseRate>
		<inverseDescription>1 Mauritanian Ouguiya = 0.026819 Swiss Franc</inverseDescription>
	</item>
</channel>

