<?xml version="1.0" encoding="utf-8"?>
<?xml-stylesheet type="text/xsl" href="https://www.floatrates.com/currency-rates.xsl" ?>
<channel>
	<title>XML Historical Foreign Exchange Rates for Swiss Franc (CHF) (10 Jul 2020)</title>
	<link>http://www.floatrates.com/currency/chf/</link>
	<xmlLink>http://www.floatrates.com/daily/chf.xml</xmlLink>
	<description>XML historical foreign exchange rates for Swiss Franc (CHF) from the Float Rates. Published at 10 Jul 2020.</description>
	<language>en</language>
	<baseCurrency>CHF</baseCurrency>
	<pubDate>Fri, 10 Jul 2020</pubDate>
	<lastBuildDate>Fri, 10 Jul 2020</lastBuildDate>
	
	<item>
		<title>1 CHF = 7.443374 CNY</title>
		<link>http://www.floatrates.com/chf/cny/</link>
		<description>1 Swiss Franc = 7.443374 Chinese Yuan</description>
		<pubDate></pubDate>
		<baseCurrency>CHF</baseCurrency>
		<baseName>Swiss Franc</baseName>
		<targetCurrency>CNY</targetCurrency>
		<targetName>Chinese Yuan</targetName>
		<exchangeRate>7.443374</exchangeRate>
		<inverseRate>0.134348</inverseRate>
		<inverseDescription>1 Chinese Yuan = 0.134348 Swiss Franc</inverseDescription>
	</item>
	<item>
		<title>1 CHF = 0.941749 EUR</title>
		<link>http://www.floatrates.com/chf/eur/</link>
		<description>1 Swiss Franc = 0.941749 Euro</description>
		<pubDate></pubDate>
		<baseCurrency>CHF</baseCurrency>
		<baseName>Swiss Franc</baseName>
		<targetCurrency>EUR</targetCurrency>
		<targetName>Euro</targetName>
		<exchangeRate>0.941749</exchangeRate>
		<inverseRate>1.061854</inverseRate>
		<inverseDescription>1 Euro = 1.061854 Swiss Franc</inverseDescription>
	</item>
	<item>
		<title>1 CHF = 113.548552 JPY</title>
		<link>http://www.floatrates.com/chf/jpy/</link>
		<description>1 Swiss Franc = 113.548552 Japanese Yen</description>
		<pubDate></pubDate>
		<baseCurrency>CHF</baseCurrency>
		<baseName>Swiss Franc</baseName>
		<targetCurrency>JPY</targetCurrency>
		<targetName>Japanese Yen</targetName>
		<exchangeRate>113.548552</exchangeRate>
		<inverseRate>0.008807</inverseRate>
		<inverseDescription>1 Japanese Yen = 0.008807 Swiss Franc</inverseDescription>
	</item>
	<item>
		<title>1 CHF = 0.843081 GBP</title>
		<link>http://www.floatrates.com/chf/gbp/</link>
		<description>1 Swiss Franc = 0.843081 U.K. Pound Sterling</description>
		<pubDate></pubDate>
		<baseCurrency>CHF</baseCurrency>
		<baseName>Swiss Franc</baseName>
		<targetCurrency>GBP</targetCurrency>
		<targetName>U.K. Pound Sterling</targetName>
		<exchangeRate>0.843081</exchangeRate>
		<inverseRate>1.186125</inverseRate>
		<inverseDescription>1 U.K. Pound Sterling = 1.186125 Swiss Franc</inverseDescription>
	</item>
	<item>
		<title>1 CHF = 1.062574 USD</title>
		<link>http://www.floatrates.com/chf/usd/</link>
		<description>1 Swiss Franc = 1.062574 U.S. Dollar</description>
		<pubDate></pubDate>
		<baseCurrency>CHF</baseCurrency>
		<baseName>Swiss Franc</baseName>
		<targetCurrency>USD</targetCurrency>
		<targetName>U.S. Dollar</targetName>
		<exchangeRate>1.062574</exchangeRate>
		<inverseRate>0.941111</inverseRate>
		<inverseDescription>1 U.S. Dollar = 0.941111 Swiss Franc</inverseDescription>
	</item>
	<item>
		<title>1 CHF = 137.002782 DZD</title>
		<link>http://www.floatrates.com/chf/dzd/</link>
		<description>1 Swiss Franc = 137.002782 Algerian Dinar</description>
		<pubDate></pubDate>
		<baseCurrency>CHF</baseCurrency>
		<baseName>Swiss Franc</baseName>
		<targetCurrency>DZD</targetCurrency>
		<targetName>Algerian Dinar</targetName>
		<exchangeRate>137.002782</exchangeRate>
		<inverseRate>0.007299</inverseRate>
		<inverseDescription>1 Algerian Dinar = 0.007299 Swiss Franc</inverseDescription>
	</item>
	<item>
		<title>1 CHF = 1.531335 AUD</title>
		<link>http://www.floatrates.com/chf/aud/</link>
		<description>1 Swiss Franc = 1.531335 Australian Dollar</description>
		<pubDate></pubDate>
		<baseCurrency>CHF</baseCurrency>
		<baseName>Swiss Franc</baseName>
		<targetCurrency>AUD</targetCurrency>
		<targetName>Australian Dollar</targetName>
		<exchangeRate>1.531335</exchangeRate>
		<inverseRate>0.653025</inverseRate>
		<inverseDescription>1 Australian Dollar = 0.653025 Swiss Franc</inverseDescription>
	</item>
	<item>
		<title>1 CHF = 12.386162 BWP</title>
		<link>http://www.floatrates.com/chf/bwp/</link>
		<description>1 Swiss Franc = 12.386162 Botswana Pula</description>
		<pubDate></pubDate>
		<baseCurrency>CHF</baseCurrency>
		<baseName>Swiss Franc</baseName>
		<targetCurrency>BWP</targetCurrency>
		<targetName>Botswana Pula</targetName>
		<exchangeRate>12.386162</exchangeRate>
		<inverseRate>0.080735</inverseRate>
		<inverseDescription>1 Botswana Pula = 0.080735 Swiss Franc</inverseDescription>
	</item>
	<item>
		<title>1 CHF = 1.477757 BND</title>
		<link>http://www.floatrates.com/chf/bnd/</link>
		<description>1 Swiss Franc = 1.477757 Brunei Dollar</description>
		<pubDate></pubDate>
		<baseCurrency>CHF</baseCurrency>
		<baseName>Swiss Franc</baseName>
		<targetCurrency>BND</targetCurrency>
		<targetName>Brunei Dollar</targetName>
		<exchangeRate>1.477757</exchangeRate>
		<inverseRate>0.676701</inverseRate>
		<inverseDescription>1 Brunei Dollar = 0.676701 Swiss Franc</inverseDescription>
	</item>
	<item>
		<title>1 CHF = 1.444181 CAD</title>
		<link>http://www.floatrates.com/chf/cad/</link>
		<description>1 Swiss Franc = 1.444181 Canadian Dollar</description>
		<pubDate></pubDate>
		<baseCurrency>CHF</baseCurrency>
		<baseName>Swiss Franc</baseName>
		<targetCurrency>CAD</targetCurrency>
		<targetName>Canadian Dollar</targetName>
		<exchangeRate>1.444181</exchangeRate>
		<inverseRate>0.692434</inverseRate>
		<inverseDescription>1 Canadian Dollar = 0.692434 Swiss Franc</inverseDescription>
	</item>
	<item>
		<title>1 CHF = 831.072895 CLP</title>
		<link>http://www.floatrates.com/chf/clp/</link>
		<description>1 Swiss Franc = 831.072895 Chilean Peso</description>
		<pubDate></pubDate>
		<baseCurrency>CHF</baseCurrency>
		<baseName>Swiss Franc</baseName>
		<targetCurrency>CLP</targetCurrency>
		<targetName>Chilean Peso</targetName>
		<exchangeRate>831.072895</exchangeRate>
		<inverseRate>0.001203</inverseRate>
		<inverseDescription>1 Chilean Peso = 0.001203 Swiss Franc</inverseDescription>
	</item>
	<item>
		<title>1 CHF = 3,860.352673 COP</title>
		<link>http://www.floatrates.com/chf/cop/</link>
		<description>1 Swiss Franc = 3,860.352673 Colombian Peso</description>
		<pubDate></pubDate>
		<baseCurrency>CHF</baseCurrency>
		<baseName>Swiss Franc</baseName>
		<targetCurrency>COP</targetCurrency>
		<targetName>Colombian Peso</targetName>
		<exchangeRate>3,860.352673</exchangeRate>
		<inverseRate>0.000259</inverseRate>
		<inverseDescription>1 Colombian Peso = 0.000259 Swiss Franc</inverseDescription>
	</item>
	<item>
		<title>1 CHF = 25.151273 CZK</title>
		<link>http://www.floatrates.com/chf/czk/</link>
		<description>1 Swiss Franc = 25.151273 Czech Koruna</description>
		<pubDate></pubDate>
		<baseCurrency>CHF</baseCurrency>
		<baseName>Swiss Franc</baseName>
		<targetCurrency>CZK</targetCurrency>
		<targetName>Czech Koruna</targetName>
		<exchangeRate>25.151273</exchangeRate>
		<inverseRate>0.039759</inverseRate>
		<inverseDescription>1 Czech Koruna = 0.039759 Swiss Franc</inverseDescription>
	</item>
	<item>
		<title>1 CHF = 6.996965 DKK</title>
		<link>http://www.floatrates.com/chf/dkk/</link>
		<description>1 Swiss Franc = 6.996965 Danish Krone</description>
		<pubDate></pubDate>
		<baseCurrency>CHF</baseCurrency>
		<baseName>Swiss Franc</baseName>
		<targetCurrency>DKK</targetCurrency>
		<targetName>Danish Krone</targetName>
		<exchangeRate>6.996965</exchangeRate>
		<inverseRate>0.142919</inverseRate>
		<inverseDescription>1 Danish Krone = 0.142919 Swiss Franc</inverseDescription>
	</item>
	<item>
		<title>1 CHF = 79.953593 INR</title>
		<link>http://www.floatrates.com/chf/inr/</link>
		<description>1 Swiss Franc = 79.953593 Indian Rupee</description>
		<pubDate></pubDate>
		<baseCurrency>CHF</baseCurrency>
		<baseName>Swiss Franc</baseName>
		<targetCurrency>INR</targetCurrency>
		<targetName>Indian Rupee</targetName>
		<exchangeRate>79.953593</exchangeRate>
		<inverseRate>0.012507</inverseRate>
		<inverseDescription>1 Indian Rupee = 0.012507 Swiss Franc</inverseDescription>
	</item>
	<item>
		<title>1 CHF = 1,275.529301 KRW</title>
		<link>http://www.floatrates.com/chf/krw/</link>
		<description>1 Swiss Franc = 1,275.529301 South Korean Won</description>
		<pubDate></pubDate>
		<baseCurrency>CHF</baseCurrency>
		<baseName>Swiss Franc</baseName>
		<targetCurrency>KRW</targetCurrency>
		<targetName>South Korean Won</targetName>
		<exchangeRate>1,275.529301</exchangeRate>
		<inverseRate>0.000784</inverseRate>
		<inverseDescription>1 South Korean Won = 0.000784 Swiss Franc</inverseDescription>
	</item>
	<item>
		<title>1 CHF = 0.326470 KWD</title>
		<link>http://www.floatrates.com/chf/kwd/</link>
		<description>1 Swiss Franc = 0.326470 Kuwaiti Dinar</description>
		<pubDate></pubDate>
		<baseCurrency>CHF</baseCurrency>
		<baseName>Swiss Franc</baseName>
		<targetCurrency>KWD</targetCurrency>
		<targetName>Kuwaiti Dinar</targetName>
		<exchangeRate>0.326470</exchangeRate>
		<inverseRate>3.063067</inverseRate>
		<inverseDescription>1 Kuwaiti Dinar = 3.063067 Swiss Franc</inverseDescription>
	</item>
	<item>
		<title>1 CHF = 4.537256 MYR</title>
		<link>http://www.floatrates.com/chf/myr/</link>
		<description>1 Swiss Franc = 4.537256 Malaysian Ringgit</description>
		<pubDate></pubDate>
		<baseCurrency>CHF</baseCurrency>
		<baseName>Swiss Franc</baseName>
		<targetCurrency>MYR</targetCurrency>
		<targetName>Malaysian Ringgit</targetName>
		<exchangeRate>4.537256</exchangeRate>
		<inverseRate>0.220398</inverseRate>
		<inverseDescription>1 Malaysian Ringgit = 0.220398 Swiss Franc</inverseDescription>
	</item>
	<item>
		<title>1 CHF = 42.643087 MUR</title>
		<link>http://www.floatrates.com/chf/mur/</link>
		<description>1 Swiss Franc = 42.643087 Mauritian Rupee</description>
		<pubDate></pubDate>
		<baseCurrency>CHF</baseCurrency>
		<baseName>Swiss Franc</baseName>
		<targetCurrency>MUR</targetCurrency>
		<targetName>Mauritian Rupee</targetName>
		<exchangeRate>42.643087</exchangeRate>
		<inverseRate>0.023450</inverseRate>
		<inverseDescription>1 Mauritian Rupee = 0.023450 Swiss Franc</inverseDescription>
	</item>
	<item>
		<title>1 CHF = 1.618925 NZD</title>
		<link>http://www.floatrates.com/chf/nzd/</link>
		<description>1 Swiss Franc = 1.618925 New Zealand Dollar</description>
		<pubDate></pubDate>
		<baseCurrency>CHF</baseCurrency>
		<baseName>Swiss Franc</baseName>
		<targetCurrency>NZD</targetCurrency>
		<targetName>New Zealand Dollar</targetName>
		<exchangeRate>1.618925</exchangeRate>
		<inverseRate>0.617694</inverseRate>
		<inverseDescription>1 New Zealand Dollar = 0.617694 Swiss Franc</inverseDescription>
	</item>
	<item>
		<title>1 CHF = 10.022874 NOK</title>
		<link>http://www.floatrates.com/chf/nok/</link>
		<description>1 Swiss Franc = 10.022874 Norwegian Krone</description>
		<pubDate></pubDate>
		<baseCurrency>CHF</baseCurrency>
		<baseName>Swiss Franc</baseName>
		<targetCurrency>NOK</targetCurrency>
		<targetName>Norwegian Krone</targetName>
		<exchangeRate>10.022874</exchangeRate>
		<inverseRate>0.099772</inverseRate>
		<inverseDescription>1 Norwegian Krone = 0.099772 Swiss Franc</inverseDescription>
	</item>
	<item>
		<title>1 CHF = 4.213793 PLN</title>
		<link>http://www.floatrates.com/chf/pln/</link>
		<description>1 Swiss Franc = 4.213793 Polish Zloty</description>
		<pubDate></pubDate>
		<baseCurrency>CHF</baseCurrency>
		<baseName>Swiss Franc</baseName>
		<targetCurrency>PLN</targetCurrency>
		<targetName>Polish Zloty</targetName>
		<exchangeRate>4.213793</exchangeRate>
		<inverseRate>0.237316</inverseRate>
		<inverseDescription>1 Polish Zloty = 0.237316 Swiss Franc</inverseDescription>
	</item>
	<item>
		<title>1 CHF = 3.985291 SAR</title>
		<link>http://www.floatrates.com/chf/sar/</link>
		<description>1 Swiss Franc = 3.985291 Saudi Riyal</description>
		<pubDate></pubDate>
		<baseCurrency>CHF</baseCurrency>
		<baseName>Swiss Franc</baseName>
		<targetCurrency>SAR</targetCurrency>
		<targetName>Saudi Riyal</targetName>
		<exchangeRate>3.985291</exchangeRate>
		<inverseRate>0.250923</inverseRate>
		<inverseDescription>1 Saudi Riyal = 0.250923 Swiss Franc</inverseDescription>
	</item>
	<item>
		<title>1 CHF = 75.512274 RUB</title>
		<link>http://www.floatrates.com/chf/rub/</link>
		<description>1 Swiss Franc = 75.512274 Russian Rouble</description>
		<pubDate></pubDate>
		<baseCurrency>CHF</baseCurrency>
		<baseName>Swiss Franc</baseName>
		<targetCurrency>RUB</targetCurrency>
		<targetName>Russian Rouble</targetName>
		<exchangeRate>75.512274</exchangeRate>
		<inverseRate>0.013243</inverseRate>
		<inverseDescription>1 Russian Rouble = 0.013243 Swiss Franc</inverseDescription>
	</item>
	<item>
		<title>1 CHF = 1.479375 SGD</title>
		<link>http://www.floatrates.com/chf/sgd/</link>
		<description>1 Swiss Franc = 1.479375 Singapore Dollar</description>
		<pubDate></pubDate>
		<baseCurrency>CHF</baseCurrency>
		<baseName>Swiss Franc</baseName>
		<targetCurrency>SGD</targetCurrency>
		<targetName>Singapore Dollar</targetName>
		<exchangeRate>1.479375</exchangeRate>
		<inverseRate>0.675961</inverseRate>
		<inverseDescription>1 Singapore Dollar = 0.675961 Swiss Franc</inverseDescription>
	</item>
	<item>
		<title>1 CHF = 17.926343 ZAR</title>
		<link>http://www.floatrates.com/chf/zar/</link>
		<description>1 Swiss Franc = 17.926343 South African Rand</description>
		<pubDate></pubDate>
		<baseCurrency>CHF</baseCurrency>
		<baseName>Swiss Franc</baseName>
		<targetCurrency>ZAR</targetCurrency>
		<targetName>South African Rand</targetName>
		<exchangeRate>17.926343</exchangeRate>
		<inverseRate>0.055784</inverseRate>
		<inverseDescription>1 South African Rand = 0.055784 Swiss Franc</inverseDescription>
	</item>
	<item>
		<title>1 CHF = 9.794025 SEK</title>
		<link>http://www.floatrates.com/chf/sek/</link>
		<description>1 Swiss Franc = 9.794025 Swedish Krona</description>
		<pubDate></pubDate>
		<baseCurrency>CHF</baseCurrency>
		<baseName>Swiss Franc</baseName>
		<targetCurrency>SEK</targetCurrency>
		<targetName>Swedish Krona</targetName>
		<exchangeRate>9.794025</exchangeRate>
		<inverseRate>0.102103</inverseRate>
		<inverseDescription>1 Swedish Krona = 0.102103 Swiss Franc</inverseDescription>
	</item>
	<item>
		<title>1 CHF = 1.000000 CHF</title>
		<link>http://www.floatrates.com/chf/chf/</link>
		<description>1 Swiss Franc = 1.000000 Swiss Franc</description>
		<pubDate></pubDate>
		<baseCurrency>CHF</baseCurrency>
		<baseName>Swiss Franc</baseName>
		<targetCurrency>CHF</targetCurrency>
		<targetName>Swiss Franc</targetName>
		<exchangeRate>1.000000</exchangeRate>
		<inverseRate>1.000000</inverseRate>
		<inverseDescription>1 Swiss Franc = 1.000000 Swiss Franc</inverseDescription>
	</item>
	<item>
		<title>1 CHF = 33.279320 THB</title>
		<link>http://www.floatrates.com/chf/thb/</link>
		<description>1 Swiss Franc = 33.279320 Thai Baht</description>
		<pubDate></pubDate>
		<baseCurrency>CHF</baseCurrency>
		<baseName>Swiss Franc</baseName>
		<targetCurrency>THB</targetCurrency>
		<targetName>Thai Baht</targetName>
		<exchangeRate>33.279320</exchangeRate>
		<inverseRate>0.030049</inverseRate>
		<inverseDescription>1 Thai Baht = 0.030049 Swiss Franc</inverseDescription>
	</item>
	<item>
		<title>1 CHF = 3.903330 AED</title>
		<link>http://www.floatrates.com/chf/aed/</link>
		<description>1 Swiss Franc = 3.903330 U.A.E Dirham</description>
		<pubDate></pubDate>
		<baseCurrency>CHF</baseCurrency>
		<baseName>Swiss Franc</baseName>
		<targetCurrency>AED</targetCurrency>
		<targetName>U.A.E Dirham</targetName>
		<exchangeRate>3.903330</exchangeRate>
		<inverseRate>0.256192</inverseRate>
		<inverseDescription>1 U.A.E Dirham = 0.256192 Swiss Franc</inverseDescription>
	</item>
	<item>
		<title>1 CHF = 2.126154 BBD</title>
		<link>http://www.floatrates.com/chf/bbd/</link>
		<description>1 Swiss Franc = 2.126154 Barbadian Dollar</description>
		<pubDate></pubDate>
		<baseCurrency>CHF</baseCurrency>
		<baseName>Swiss Franc</baseName>
		<targetCurrency>BBD</targetCurrency>
		<targetName>Barbadian Dollar</targetName>
		<exchangeRate>2.126154</exchangeRate>
		<inverseRate>0.470333</inverseRate>
		<inverseDescription>1 Barbadian Dollar = 0.470333 Swiss Franc</inverseDescription>
	</item>
	<item>
		<title>1 CHF = 0.847346 GIP</title>
		<link>http://www.floatrates.com/chf/gip/</link>
		<description>1 Swiss Franc = 0.847346 Gibraltar pound</description>
		<pubDate></pubDate>
		<baseCurrency>CHF</baseCurrency>
		<baseName>Swiss Franc</baseName>
		<targetCurrency>GIP</targetCurrency>
		<targetName>Gibraltar pound</targetName>
		<exchangeRate>0.847346</exchangeRate>
		<inverseRate>1.180155</inverseRate>
		<inverseDescription>1 Gibraltar pound = 1.180155 Swiss Franc</inverseDescription>
	</item>
	<item>
		<title>1 CHF = 3.870367 QAR</title>
		<link>http://www.floatrates.com/chf/qar/</link>
		<description>1 Swiss Franc = 3.870367 Qatari Rial</description>
		<pubDate></pubDate>
		<baseCurrency>CHF</baseCurrency>
		<baseName>Swiss Franc</baseName>
		<targetCurrency>QAR</targetCurrency>
		<targetName>Qatari Rial</targetName>
		<exchangeRate>3.870367</exchangeRate>
		<inverseRate>0.258373</inverseRate>
		<inverseDescription>1 Qatari Rial = 0.258373 Swiss Franc</inverseDescription>
	</item>
	<item>
		<title>1 CHF = 0.400790 BHD</title>
		<link>http://www.floatrates.com/chf/bhd/</link>
		<description>1 Swiss Franc = 0.400790 Bahrain Dinar</description>
		<pubDate></pubDate>
		<baseCurrency>CHF</baseCurrency>
		<baseName>Swiss Franc</baseName>
		<targetCurrency>BHD</targetCurrency>
		<targetName>Bahrain Dinar</targetName>
		<exchangeRate>0.400790</exchangeRate>
		<inverseRate>2.495075</inverseRate>
		<inverseDescription>1 Bahrain Dinar = 2.495075 Swiss Franc</inverseDescription>
	</item>
	<item>
		<title>1 CHF = 3.041215 TND</title>
		<link>http://www.floatrates.com/chf/tnd/</link>
		<description>1 Swiss Franc = 3.041215 Tunisian Dinar</description>
		<pubDate></pubDate>
		<baseCurrency>CHF</baseCurrency>
		<baseName>Swiss Franc</baseName>
		<targetCurrency>TND</targetCurrency>
		<targetName>Tunisian Dinar</targetName>
		<exchangeRate>3.041215</exchangeRate>
		<inverseRate>0.328816</inverseRate>
		<inverseDescription>1 Tunisian Dinar = 0.328816 Swiss Franc</inverseDescription>
	</item>
	<item>
		<title>1 CHF = 1.489061 LYD</title>
		<link>http://www.floatrates.com/chf/lyd/</link>
		<description>1 Swiss Franc = 1.489061 Libyan Dinar</description>
		<pubDate></pubDate>
		<baseCurrency>CHF</baseCurrency>
		<baseName>Swiss Franc</baseName>
		<targetCurrency>LYD</targetCurrency>
		<targetName>Libyan Dinar</targetName>
		<exchangeRate>1.489061</exchangeRate>
		<inverseRate>0.671564</inverseRate>
		<inverseDescription>1 Libyan Dinar = 0.671564 Swiss Franc</inverseDescription>
	</item>
	<item>
		<title>1 CHF = 39.989419 MRO</title>
		<link>http://www.floatrates.com/chf/mro/</link>
		<description>1 Swiss Franc = 39.989419 Mauritanian Ouguiya</description>
		<pubDate></pubDate>
		<baseCurrency>CHF</baseCurrency>
		<baseName>Swiss Franc</baseName>
		<targetCurrency>MRO</targetCurrency>
		<targetName>Mauritanian Ouguiya</targetName>
		<exchangeRate>39.989419</exchangeRate>
		<inverseRate>0.025007</inverseRate>
		<inverseDescription>1 Mauritanian Ouguiya = 0.025007 Swiss Franc</inverseDescription>
	</item>
	<item>
		<title>1 CHF = 0.409220 OMR</title>
		<link>http://www.floatrates.com/chf/omr/</link>
		<description>1 Swiss Franc = 0.409220 Omani Rial</description>
		<pubDate></pubDate>
		<baseCurrency>CHF</baseCurrency>
		<baseName>Swiss Franc</baseName>
		<targetCurrency>OMR</targetCurrency>
		<targetName>Omani Rial</targetName>
		<exchangeRate>0.409220</exchangeRate>
		<inverseRate>2.443674</inverseRate>
		<inverseDescription>1 Omani Rial = 2.443674 Swiss Franc</inverseDescription>
	</item>
	<item>
		<title>1 CHF = 5.694631 BRL</title>
		<link>http://www.floatrates.com/chf/brl/</link>
		<description>1 Swiss Franc = 5.694631 Brazilian Real</description>
		<pubDate></pubDate>
		<baseCurrency>CHF</baseCurrency>
		<baseName>Swiss Franc</baseName>
		<targetCurrency>BRL</targetCurrency>
		<targetName>Brazilian Real</targetName>
		<exchangeRate>5.694631</exchangeRate>
		<inverseRate>0.175604</inverseRate>
		<inverseDescription>1 Brazilian Real = 0.175604 Swiss Franc</inverseDescription>
	</item>
	<item>
		<title>1 CHF = 7.294715 TRY</title>
		<link>http://www.floatrates.com/chf/try/</link>
		<description>1 Swiss Franc = 7.294715 Turkish Lira</description>
		<pubDate></pubDate>
		<baseCurrency>CHF</baseCurrency>
		<baseName>Swiss Franc</baseName>
		<targetCurrency>TRY</targetCurrency>
		<targetName>Turkish Lira</targetName>
		<exchangeRate>7.294715</exchangeRate>
		<inverseRate>0.137086</inverseRate>
		<inverseDescription>1 Turkish Lira = 0.137086 Swiss Franc</inverseDescription>
	</item>
	<item>
		<title>1 CHF = 17.003721 EGP</title>
		<link>http://www.floatrates.com/chf/egp/</link>
		<description>1 Swiss Franc = 17.003721 Egyptian Pound</description>
		<pubDate></pubDate>
		<baseCurrency>CHF</baseCurrency>
		<baseName>Swiss Franc</baseName>
		<targetCurrency>EGP</targetCurrency>
		<targetName>Egyptian Pound</targetName>
		<exchangeRate>17.003721</exchangeRate>
		<inverseRate>0.058811</inverseRate>
		<inverseDescription>1 Egyptian Pound = 0.058811 Swiss Franc</inverseDescription>
	</item>
	<item>
		<title>1 CHF = 0.753451 JOD</title>
		<link>http://www.floatrates.com/chf/jod/</link>
		<description>1 Swiss Franc = 0.753451 Jordanian Dinar</description>
		<pubDate></pubDate>
		<baseCurrency>CHF</baseCurrency>
		<baseName>Swiss Franc</baseName>
		<targetCurrency>JOD</targetCurrency>
		<targetName>Jordanian Dinar</targetName>
		<exchangeRate>0.753451</exchangeRate>
		<inverseRate>1.327227</inverseRate>
		<inverseDescription>1 Jordanian Dinar = 1.327227 Swiss Franc</inverseDescription>
	</item>
	<item>
		<title>1 CHF = 619.160175 XOF</title>
		<link>http://www.floatrates.com/chf/xof/</link>
		<description>1 Swiss Franc = 619.160175 West African CFA Franc</description>
		<pubDate></pubDate>
		<baseCurrency>CHF</baseCurrency>
		<baseName>Swiss Franc</baseName>
		<targetCurrency>XOF</targetCurrency>
		<targetName>West African CFA Franc</targetName>
		<exchangeRate>619.160175</exchangeRate>
		<inverseRate>0.001615</inverseRate>
		<inverseDescription>1 West African CFA Franc = 0.001615 Swiss Franc</inverseDescription>
	</item>
	<item>
		<title>1 CHF = 10.347345 MAD</title>
		<link>http://www.floatrates.com/chf/mad/</link>
		<description>1 Swiss Franc = 10.347345 Moroccan Dirham</description>
		<pubDate></pubDate>
		<baseCurrency>CHF</baseCurrency>
		<baseName>Swiss Franc</baseName>
		<targetCurrency>MAD</targetCurrency>
		<targetName>Moroccan Dirham</targetName>
		<exchangeRate>10.347345</exchangeRate>
		<inverseRate>0.096643</inverseRate>
		<inverseDescription>1 Moroccan Dirham = 0.096643 Swiss Franc</inverseDescription>
	</item>
	<item>
		<title>1 CHF = 15,357.867628 IDR</title>
		<link>http://www.floatrates.com/chf/idr/</link>
		<description>1 Swiss Franc = 15,357.867628 Indonesian Rupiah</description>
		<pubDate></pubDate>
		<baseCurrency>CHF</baseCurrency>
		<baseName>Swiss Franc</baseName>
		<targetCurrency>IDR</targetCurrency>
		<targetName>Indonesian Rupiah</targetName>
		<exchangeRate>15,357.867628</exchangeRate>
		<inverseRate>0.000065</inverseRate>
		<inverseDescription>1 Indonesian Rupiah = 0.000065 Swiss Franc</inverseDescription>
	</item>
	<item>
		<title>1 CHF = 31.359338 TWD</title>
		<link>http://www.floatrates.com/chf/twd/</link>
		<description>1 Swiss Franc = 31.359338 New Taiwan Dollar </description>
		<pubDate></pubDate>
		<baseCurrency>CHF</baseCurrency>
		<baseName>Swiss Franc</baseName>
		<targetCurrency>TWD</targetCurrency>
		<targetName>New Taiwan Dollar </targetName>
		<exchangeRate>31.359338</exchangeRate>
		<inverseRate>0.031888</inverseRate>
		<inverseDescription>1 New Taiwan Dollar  = 0.031888 Swiss Franc</inverseDescription>
	</item>
	<item>
		<title>1 CHF = 24,645.716226 VND</title>
		<link>http://www.floatrates.com/chf/vnd/</link>
		<description>1 Swiss Franc = 24,645.716226 Vietnamese Dong</description>
		<pubDate></pubDate>
		<baseCurrency>CHF</baseCurrency>
		<baseName>Swiss Franc</baseName>
		<targetCurrency>VND</targetCurrency>
		<targetName>Vietnamese Dong</targetName>
		<exchangeRate>24,645.716226</exchangeRate>
		<inverseRate>0.000041</inverseRate>
		<inverseDescription>1 Vietnamese Dong = 0.000041 Swiss Franc</inverseDescription>
	</item>
	<item>
		<title>1 CHF = 8.235318 HKD</title>
		<link>http://www.floatrates.com/chf/hkd/</link>
		<description>1 Swiss Franc = 8.235318 Hong Kong Dollar</description>
		<pubDate></pubDate>
		<baseCurrency>CHF</baseCurrency>
		<baseName>Swiss Franc</baseName>
		<targetCurrency>HKD</targetCurrency>
		<targetName>Hong Kong Dollar</targetName>
		<exchangeRate>8.235318</exchangeRate>
		<inverseRate>0.121428</inverseRate>
		<inverseDescription>1 Hong Kong Dollar = 0.121428 Swiss Franc</inverseDescription>
	</item>
	<item>
		<title>1 CHF = 3.689714 PGK</title>
		<link>http://www.floatrates.com/chf/pgk/</link>
		<description>1 Swiss Franc = 3.689714 Papua New Guinean kina</description>
		<pubDate></pubDate>
		<baseCurrency>CHF</baseCurrency>
		<baseName>Swiss Franc</baseName>
		<targetCurrency>PGK</targetCurrency>
		<targetName>Papua New Guinean kina</targetName>
		<exchangeRate>3.689714</exchangeRate>
		<inverseRate>0.271024</inverseRate>
		<inverseDescription>1 Papua New Guinean kina = 0.271024 Swiss Franc</inverseDescription>
	</item>
	<item>
		<title>1 CHF = 36.884268 NIO</title>
		<link>http://www.floatrates.com/chf/nio/</link>
		<description>1 Swiss Franc = 36.884268 Nicaraguan Córdoba</description>
		<pubDate></pubDate>
		<baseCurrency>CHF</baseCurrency>
		<baseName>Swiss Franc</baseName>
		<targetCurrency>NIO</targetCurrency>
		<targetName>Nicaraguan Córdoba</targetName>
		<exchangeRate>36.884268</exchangeRate>
		<inverseRate>0.027112</inverseRate>
		<inverseDescription>1 Nicaraguan Córdoba = 0.027112 Swiss Franc</inverseDescription>
	</item>
	<item>
		<title>1 CHF = 3.675027 ILS</title>
		<link>http://www.floatrates.com/chf/ils/</link>
		<description>1 Swiss Franc = 3.675027 Israeli New Sheqel</description>
		<pubDate></pubDate>
		<baseCurrency>CHF</baseCurrency>
		<baseName>Swiss Franc</baseName>
		<targetCurrency>ILS</targetCurrency>
		<targetName>Israeli New Sheqel</targetName>
		<exchangeRate>3.675027</exchangeRate>
		<inverseRate>0.272107</inverseRate>
		<inverseDescription>1 Israeli New Sheqel = 0.272107 Swiss Franc</inverseDescription>
	</item>
	<item>
		<title>1 CHF = 1,610.056040 LBP</title>
		<link>http://www.floatrates.com/chf/lbp/</link>
		<description>1 Swiss Franc = 1,610.056040 Lebanese Pound</description>
		<pubDate></pubDate>
		<baseCurrency>CHF</baseCurrency>
		<baseName>Swiss Franc</baseName>
		<targetCurrency>LBP</targetCurrency>
		<targetName>Lebanese Pound</targetName>
		<exchangeRate>1,610.056040</exchangeRate>
		<inverseRate>0.000621</inverseRate>
		<inverseDescription>1 Lebanese Pound = 0.000621 Swiss Franc</inverseDescription>
	</item>
	<item>
		<title>1 CHF = 333.216152 HUF</title>
		<link>http://www.floatrates.com/chf/huf/</link>
		<description>1 Swiss Franc = 333.216152 Hungarian Forint</description>
		<pubDate></pubDate>
		<baseCurrency>CHF</baseCurrency>
		<baseName>Swiss Franc</baseName>
		<targetCurrency>HUF</targetCurrency>
		<targetName>Hungarian Forint</targetName>
		<exchangeRate>333.216152</exchangeRate>
		<inverseRate>0.003001</inverseRate>
		<inverseDescription>1 Hungarian Forint = 0.003001 Swiss Franc</inverseDescription>
	</item>
	<item>
		<title>1 CHF = 28.637653 UAH</title>
		<link>http://www.floatrates.com/chf/uah/</link>
		<description>1 Swiss Franc = 28.637653 Ukrainian Hryvnia</description>
		<pubDate></pubDate>
		<baseCurrency>CHF</baseCurrency>
		<baseName>Swiss Franc</baseName>
		<targetCurrency>UAH</targetCurrency>
		<targetName>Ukrainian Hryvnia</targetName>
		<exchangeRate>28.637653</exchangeRate>
		<inverseRate>0.034919</inverseRate>
		<inverseDescription>1 Ukrainian Hryvnia = 0.034919 Swiss Franc</inverseDescription>
	</item>
	<item>
		<title>1 CHF = 149.799369 ISK</title>
		<link>http://www.floatrates.com/chf/isk/</link>
		<description>1 Swiss Franc = 149.799369 Icelandic Krona</description>
		<pubDate></pubDate>
		<baseCurrency>CHF</baseCurrency>
		<baseName>Swiss Franc</baseName>
		<targetCurrency>ISK</targetCurrency>
		<targetName>Icelandic Krona</targetName>
		<exchangeRate>149.799369</exchangeRate>
		<inverseRate>0.006676</inverseRate>
		<inverseDescription>1 Icelandic Krona = 0.006676 Swiss Franc</inverseDescription>
	</item>
	<item>
		<title>1 CHF = 7.098291 HRK</title>
		<link>http://www.floatrates.com/chf/hrk/</link>
		<description>1 Swiss Franc = 7.098291 Croatian Kuna</description>
		<pubDate></pubDate>
		<baseCurrency>CHF</baseCurrency>
		<baseName>Swiss Franc</baseName>
		<targetCurrency>HRK</targetCurrency>
		<targetName>Croatian Kuna</targetName>
		<exchangeRate>7.098291</exchangeRate>
		<inverseRate>0.140879</inverseRate>
		<inverseDescription>1 Croatian Kuna = 0.140879 Swiss Franc</inverseDescription>
	</item>
	<item>
		<title>1 CHF = 4.562179 RON</title>
		<link>http://www.floatrates.com/chf/ron/</link>
		<description>1 Swiss Franc = 4.562179 Romanian New Leu</description>
		<pubDate></pubDate>
		<baseCurrency>CHF</baseCurrency>
		<baseName>Swiss Franc</baseName>
		<targetCurrency>RON</targetCurrency>
		<targetName>Romanian New Leu</targetName>
		<exchangeRate>4.562179</exchangeRate>
		<inverseRate>0.219194</inverseRate>
		<inverseDescription>1 Romanian New Leu = 0.219194 Swiss Franc</inverseDescription>
	</item>
	<item>
		<title>1 CHF = 1.842629 BGN</title>
		<link>http://www.floatrates.com/chf/bgn/</link>
		<description>1 Swiss Franc = 1.842629 Bulgarian Lev</description>
		<pubDate></pubDate>
		<baseCurrency>CHF</baseCurrency>
		<baseName>Swiss Franc</baseName>
		<targetCurrency>BGN</targetCurrency>
		<targetName>Bulgarian Lev</targetName>
		<exchangeRate>1.842629</exchangeRate>
		<inverseRate>0.542703</inverseRate>
		<inverseDescription>1 Bulgarian Lev = 0.542703 Swiss Franc</inverseDescription>
	</item>
	<item>
		<title>1 CHF = 52.572534 PHP</title>
		<link>http://www.floatrates.com/chf/php/</link>
		<description>1 Swiss Franc = 52.572534 Philippine Peso</description>
		<pubDate></pubDate>
		<baseCurrency>CHF</baseCurrency>
		<baseName>Swiss Franc</baseName>
		<targetCurrency>PHP</targetCurrency>
		<targetName>Philippine Peso</targetName>
		<exchangeRate>52.572534</exchangeRate>
		<inverseRate>0.019021</inverseRate>
		<inverseDescription>1 Philippine Peso = 0.019021 Swiss Franc</inverseDescription>
	</item>
	<item>
		<title>1 CHF = 24.071133 MXN</title>
		<link>http://www.floatrates.com/chf/mxn/</link>
		<description>1 Swiss Franc = 24.071133 Mexican Peso</description>
		<pubDate></pubDate>
		<baseCurrency>CHF</baseCurrency>
		<baseName>Swiss Franc</baseName>
		<targetCurrency>MXN</targetCurrency>
		<targetName>Mexican Peso</targetName>
		<exchangeRate>24.071133</exchangeRate>
		<inverseRate>0.041544</inverseRate>
		<inverseDescription>1 Mexican Peso = 0.041544 Swiss Franc</inverseDescription>
	</item>
	<item>
		<title>1 CHF = 81.961968 AFN</title>
		<link>http://www.floatrates.com/chf/afn/</link>
		<description>1 Swiss Franc = 81.961968 Afghan afghani</description>
		<pubDate></pubDate>
		<baseCurrency>CHF</baseCurrency>
		<baseName>Swiss Franc</baseName>
		<targetCurrency>AFN</targetCurrency>
		<targetName>Afghan afghani</targetName>
		<exchangeRate>81.961968</exchangeRate>
		<inverseRate>0.012201</inverseRate>
		<inverseDescription>1 Afghan afghani = 0.012201 Swiss Franc</inverseDescription>
	</item>
	<item>
		<title>1 CHF = 4,113.946523 MGA</title>
		<link>http://www.floatrates.com/chf/mga/</link>
		<description>1 Swiss Franc = 4,113.946523 Malagasy ariary</description>
		<pubDate></pubDate>
		<baseCurrency>CHF</baseCurrency>
		<baseName>Swiss Franc</baseName>
		<targetCurrency>MGA</targetCurrency>
		<targetName>Malagasy ariary</targetName>
		<exchangeRate>4,113.946523</exchangeRate>
		<inverseRate>0.000243</inverseRate>
		<inverseDescription>1 Malagasy ariary = 0.000243 Swiss Franc</inverseDescription>
	</item>
	<item>
		<title>1 CHF = 1.062038 PAB</title>
		<link>http://www.floatrates.com/chf/pab/</link>
		<description>1 Swiss Franc = 1.062038 Panamanian Balboa</description>
		<pubDate></pubDate>
		<baseCurrency>CHF</baseCurrency>
		<baseName>Swiss Franc</baseName>
		<targetCurrency>PAB</targetCurrency>
		<targetName>Panamanian Balboa</targetName>
		<exchangeRate>1.062038</exchangeRate>
		<inverseRate>0.941586</inverseRate>
		<inverseDescription>1 Panamanian Balboa = 0.941586 Swiss Franc</inverseDescription>
	</item>
	<item>
		<title>1 CHF = 37.479370 ETB</title>
		<link>http://www.floatrates.com/chf/etb/</link>
		<description>1 Swiss Franc = 37.479370 Ethiopian birr</description>
		<pubDate></pubDate>
		<baseCurrency>CHF</baseCurrency>
		<baseName>Swiss Franc</baseName>
		<targetCurrency>ETB</targetCurrency>
		<targetName>Ethiopian birr</targetName>
		<exchangeRate>37.479370</exchangeRate>
		<inverseRate>0.026681</inverseRate>
		<inverseDescription>1 Ethiopian birr = 0.026681 Swiss Franc</inverseDescription>
	</item>
	<item>
		<title>1 CHF = 223,652.357055 VES</title>
		<link>http://www.floatrates.com/chf/ves/</link>
		<description>1 Swiss Franc = 223,652.357055 Venezuelan Bolivar</description>
		<pubDate></pubDate>
		<baseCurrency>CHF</baseCurrency>
		<baseName>Swiss Franc</baseName>
		<targetCurrency>VES</targetCurrency>
		<targetName>Venezuelan Bolivar</targetName>
		<exchangeRate>223,652.357055</exchangeRate>
		<inverseRate>0.000004</inverseRate>
		<inverseDescription>1 Venezuelan Bolivar = 0.000004 Swiss Franc</inverseDescription>
	</item>
	<item>
		<title>1 CHF = 7.345107 BOB</title>
		<link>http://www.floatrates.com/chf/bob/</link>
		<description>1 Swiss Franc = 7.345107 Bolivian Boliviano</description>
		<pubDate></pubDate>
		<baseCurrency>CHF</baseCurrency>
		<baseName>Swiss Franc</baseName>
		<targetCurrency>BOB</targetCurrency>
		<targetName>Bolivian Boliviano</targetName>
		<exchangeRate>7.345107</exchangeRate>
		<inverseRate>0.136145</inverseRate>
		<inverseDescription>1 Bolivian Boliviano = 0.136145 Swiss Franc</inverseDescription>
	</item>
	<item>
		<title>1 CHF = 619.727088 CRC</title>
		<link>http://www.floatrates.com/chf/crc/</link>
		<description>1 Swiss Franc = 619.727088 Costa Rican Colón</description>
		<pubDate></pubDate>
		<baseCurrency>CHF</baseCurrency>
		<baseName>Swiss Franc</baseName>
		<targetCurrency>CRC</targetCurrency>
		<targetName>Costa Rican Colón</targetName>
		<exchangeRate>619.727088</exchangeRate>
		<inverseRate>0.001614</inverseRate>
		<inverseDescription>1 Costa Rican Colón = 0.001614 Swiss Franc</inverseDescription>
	</item>
	<item>
		<title>1 CHF = 9.305680 SVC</title>
		<link>http://www.floatrates.com/chf/svc/</link>
		<description>1 Swiss Franc = 9.305680 Salvadoran colon</description>
		<pubDate></pubDate>
		<baseCurrency>CHF</baseCurrency>
		<baseName>Swiss Franc</baseName>
		<targetCurrency>SVC</targetCurrency>
		<targetName>Salvadoran colon</targetName>
		<exchangeRate>9.305680</exchangeRate>
		<inverseRate>0.107461</inverseRate>
		<inverseDescription>1 Salvadoran colon = 0.107461 Swiss Franc</inverseDescription>
	</item>
	<item>
		<title>1 CHF = 55.723297 GMD</title>
		<link>http://www.floatrates.com/chf/gmd/</link>
		<description>1 Swiss Franc = 55.723297 Gambian dalasi</description>
		<pubDate></pubDate>
		<baseCurrency>CHF</baseCurrency>
		<baseName>Swiss Franc</baseName>
		<targetCurrency>GMD</targetCurrency>
		<targetName>Gambian dalasi</targetName>
		<exchangeRate>55.723297</exchangeRate>
		<inverseRate>0.017946</inverseRate>
		<inverseDescription>1 Gambian dalasi = 0.017946 Swiss Franc</inverseDescription>
	</item>
	<item>
		<title>1 CHF = 58.088321 MKD</title>
		<link>http://www.floatrates.com/chf/mkd/</link>
		<description>1 Swiss Franc = 58.088321 Macedonian denar</description>
		<pubDate></pubDate>
		<baseCurrency>CHF</baseCurrency>
		<baseName>Swiss Franc</baseName>
		<targetCurrency>MKD</targetCurrency>
		<targetName>Macedonian denar</targetName>
		<exchangeRate>58.088321</exchangeRate>
		<inverseRate>0.017215</inverseRate>
		<inverseDescription>1 Macedonian denar = 0.017215 Swiss Franc</inverseDescription>
	</item>
	<item>
		<title>1 CHF = 1,273.371294 IQD</title>
		<link>http://www.floatrates.com/chf/iqd/</link>
		<description>1 Swiss Franc = 1,273.371294 Iraqi dinar</description>
		<pubDate></pubDate>
		<baseCurrency>CHF</baseCurrency>
		<baseName>Swiss Franc</baseName>
		<targetCurrency>IQD</targetCurrency>
		<targetName>Iraqi dinar</targetName>
		<exchangeRate>1,273.371294</exchangeRate>
		<inverseRate>0.000785</inverseRate>
		<inverseDescription>1 Iraqi dinar = 0.000785 Swiss Franc</inverseDescription>
	</item>
	<item>
		<title>1 CHF = 111.407690 RSD</title>
		<link>http://www.floatrates.com/chf/rsd/</link>
		<description>1 Swiss Franc = 111.407690 Serbian Dinar</description>
		<pubDate></pubDate>
		<baseCurrency>CHF</baseCurrency>
		<baseName>Swiss Franc</baseName>
		<targetCurrency>RSD</targetCurrency>
		<targetName>Serbian Dinar</targetName>
		<exchangeRate>111.407690</exchangeRate>
		<inverseRate>0.008976</inverseRate>
		<inverseDescription>1 Serbian Dinar = 0.008976 Swiss Franc</inverseDescription>
	</item>
	<item>
		<title>1 CHF = 23.746794 STN</title>
		<link>http://www.floatrates.com/chf/stn/</link>
		<description>1 Swiss Franc = 23.746794 São Tomé and Príncipe Dobra</description>
		<pubDate></pubDate>
		<baseCurrency>CHF</baseCurrency>
		<baseName>Swiss Franc</baseName>
		<targetCurrency>STN</targetCurrency>
		<targetName>São Tomé and Príncipe Dobra</targetName>
		<exchangeRate>23.746794</exchangeRate>
		<inverseRate>0.042111</inverseRate>
		<inverseDescription>1 São Tomé and Príncipe Dobra = 0.042111 Swiss Franc</inverseDescription>
	</item>
	<item>
		<title>1 CHF = 1.062038 BSD</title>
		<link>http://www.floatrates.com/chf/bsd/</link>
		<description>1 Swiss Franc = 1.062038 Bahamian Dollar</description>
		<pubDate></pubDate>
		<baseCurrency>CHF</baseCurrency>
		<baseName>Swiss Franc</baseName>
		<targetCurrency>BSD</targetCurrency>
		<targetName>Bahamian Dollar</targetName>
		<exchangeRate>1.062038</exchangeRate>
		<inverseRate>0.941586</inverseRate>
		<inverseDescription>1 Bahamian Dollar = 0.941586 Swiss Franc</inverseDescription>
	</item>
	<item>
		<title>1 CHF = 2.142550 BZD</title>
		<link>http://www.floatrates.com/chf/bzd/</link>
		<description>1 Swiss Franc = 2.142550 Belize dollar</description>
		<pubDate></pubDate>
		<baseCurrency>CHF</baseCurrency>
		<baseName>Swiss Franc</baseName>
		<targetCurrency>BZD</targetCurrency>
		<targetName>Belize dollar</targetName>
		<exchangeRate>2.142550</exchangeRate>
		<inverseRate>0.466734</inverseRate>
		<inverseDescription>1 Belize dollar = 0.466734 Swiss Franc</inverseDescription>
	</item>
	<item>
		<title>1 CHF = 2.297993 FJD</title>
		<link>http://www.floatrates.com/chf/fjd/</link>
		<description>1 Swiss Franc = 2.297993 Fiji Dollar</description>
		<pubDate></pubDate>
		<baseCurrency>CHF</baseCurrency>
		<baseName>Swiss Franc</baseName>
		<targetCurrency>FJD</targetCurrency>
		<targetName>Fiji Dollar</targetName>
		<exchangeRate>2.297993</exchangeRate>
		<inverseRate>0.435162</inverseRate>
		<inverseDescription>1 Fiji Dollar = 0.435162 Swiss Franc</inverseDescription>
	</item>
	<item>
		<title>1 CHF = 222.293348 GYD</title>
		<link>http://www.floatrates.com/chf/gyd/</link>
		<description>1 Swiss Franc = 222.293348 Guyanese dollar</description>
		<pubDate></pubDate>
		<baseCurrency>CHF</baseCurrency>
		<baseName>Swiss Franc</baseName>
		<targetCurrency>GYD</targetCurrency>
		<targetName>Guyanese dollar</targetName>
		<exchangeRate>222.293348</exchangeRate>
		<inverseRate>0.004499</inverseRate>
		<inverseDescription>1 Guyanese dollar = 0.004499 Swiss Franc</inverseDescription>
	</item>
	<item>
		<title>1 CHF = 149.385860 JMD</title>
		<link>http://www.floatrates.com/chf/jmd/</link>
		<description>1 Swiss Franc = 149.385860 Jamaican Dollar</description>
		<pubDate></pubDate>
		<baseCurrency>CHF</baseCurrency>
		<baseName>Swiss Franc</baseName>
		<targetCurrency>JMD</targetCurrency>
		<targetName>Jamaican Dollar</targetName>
		<exchangeRate>149.385860</exchangeRate>
		<inverseRate>0.006694</inverseRate>
		<inverseDescription>1 Jamaican Dollar = 0.006694 Swiss Franc</inverseDescription>
	</item>
	<item>
		<title>1 CHF = 212.761679 LRD</title>
		<link>http://www.floatrates.com/chf/lrd/</link>
		<description>1 Swiss Franc = 212.761679 Liberian dollar</description>
		<pubDate></pubDate>
		<baseCurrency>CHF</baseCurrency>
		<baseName>Swiss Franc</baseName>
		<targetCurrency>LRD</targetCurrency>
		<targetName>Liberian dollar</targetName>
		<exchangeRate>212.761679</exchangeRate>
		<inverseRate>0.004700</inverseRate>
		<inverseDescription>1 Liberian dollar = 0.004700 Swiss Franc</inverseDescription>
	</item>
	<item>
		<title>1 CHF = 18.126856 NAD</title>
		<link>http://www.floatrates.com/chf/nad/</link>
		<description>1 Swiss Franc = 18.126856 Namibian dollar</description>
		<pubDate></pubDate>
		<baseCurrency>CHF</baseCurrency>
		<baseName>Swiss Franc</baseName>
		<targetCurrency>NAD</targetCurrency>
		<targetName>Namibian dollar</targetName>
		<exchangeRate>18.126856</exchangeRate>
		<inverseRate>0.055167</inverseRate>
		<inverseDescription>1 Namibian dollar = 0.055167 Swiss Franc</inverseDescription>
	</item>
	<item>
		<title>1 CHF = 7.945457 SRD</title>
		<link>http://www.floatrates.com/chf/srd/</link>
		<description>1 Swiss Franc = 7.945457 Surinamese dollar</description>
		<pubDate></pubDate>
		<baseCurrency>CHF</baseCurrency>
		<baseName>Swiss Franc</baseName>
		<targetCurrency>SRD</targetCurrency>
		<targetName>Surinamese dollar</targetName>
		<exchangeRate>7.945457</exchangeRate>
		<inverseRate>0.125858</inverseRate>
		<inverseDescription>1 Surinamese dollar = 0.125858 Swiss Franc</inverseDescription>
	</item>
	<item>
		<title>1 CHF = 7.187649 TTD</title>
		<link>http://www.floatrates.com/chf/ttd/</link>
		<description>1 Swiss Franc = 7.187649 Trinidad Tobago Dollar</description>
		<pubDate></pubDate>
		<baseCurrency>CHF</baseCurrency>
		<baseName>Swiss Franc</baseName>
		<targetCurrency>TTD</targetCurrency>
		<targetName>Trinidad Tobago Dollar</targetName>
		<exchangeRate>7.187649</exchangeRate>
		<inverseRate>0.139128</inverseRate>
		<inverseDescription>1 Trinidad Tobago Dollar = 0.139128 Swiss Franc</inverseDescription>
	</item>
	<item>
		<title>1 CHF = 2.881254 XCD</title>
		<link>http://www.floatrates.com/chf/xcd/</link>
		<description>1 Swiss Franc = 2.881254 East Caribbean Dollar</description>
		<pubDate></pubDate>
		<baseCurrency>CHF</baseCurrency>
		<baseName>Swiss Franc</baseName>
		<targetCurrency>XCD</targetCurrency>
		<targetName>East Caribbean Dollar</targetName>
		<exchangeRate>2.881254</exchangeRate>
		<inverseRate>0.347071</inverseRate>
		<inverseDescription>1 East Caribbean Dollar = 0.347071 Swiss Franc</inverseDescription>
	</item>
	<item>
		<title>1 CHF = 8.705686 SBD</title>
		<link>http://www.floatrates.com/chf/sbd/</link>
		<description>1 Swiss Franc = 8.705686 Solomon Islands dollar</description>
		<pubDate></pubDate>
		<baseCurrency>CHF</baseCurrency>
		<baseName>Swiss Franc</baseName>
		<targetCurrency>SBD</targetCurrency>
		<targetName>Solomon Islands dollar</targetName>
		<exchangeRate>8.705686</exchangeRate>
		<inverseRate>0.114867</inverseRate>
		<inverseDescription>1 Solomon Islands dollar = 0.114867 Swiss Franc</inverseDescription>
	</item>
	<item>
		<title>1 CHF = 517.411842 AMD</title>
		<link>http://www.floatrates.com/chf/amd/</link>
		<description>1 Swiss Franc = 517.411842 Armenia Dram</description>
		<pubDate></pubDate>
		<baseCurrency>CHF</baseCurrency>
		<baseName>Swiss Franc</baseName>
		<targetCurrency>AMD</targetCurrency>
		<targetName>Armenia Dram</targetName>
		<exchangeRate>517.411842</exchangeRate>
		<inverseRate>0.001933</inverseRate>
		<inverseDescription>1 Armenia Dram = 0.001933 Swiss Franc</inverseDescription>
	</item>
	<item>
		<title>1 CHF = 105.846262 CVE</title>
		<link>http://www.floatrates.com/chf/cve/</link>
		<description>1 Swiss Franc = 105.846262 Cape Verde escudo</description>
		<pubDate></pubDate>
		<baseCurrency>CHF</baseCurrency>
		<baseName>Swiss Franc</baseName>
		<targetCurrency>CVE</targetCurrency>
		<targetName>Cape Verde escudo</targetName>
		<exchangeRate>105.846262</exchangeRate>
		<inverseRate>0.009448</inverseRate>
		<inverseDescription>1 Cape Verde escudo = 0.009448 Swiss Franc</inverseDescription>
	</item>
	<item>
		<title>1 CHF = 1.923687 AWG</title>
		<link>http://www.floatrates.com/chf/awg/</link>
		<description>1 Swiss Franc = 1.923687 Aruban florin</description>
		<pubDate></pubDate>
		<baseCurrency>CHF</baseCurrency>
		<baseName>Swiss Franc</baseName>
		<targetCurrency>AWG</targetCurrency>
		<targetName>Aruban florin</targetName>
		<exchangeRate>1.923687</exchangeRate>
		<inverseRate>0.519835</inverseRate>
		<inverseDescription>1 Aruban florin = 0.519835 Swiss Franc</inverseDescription>
	</item>
	<item>
		<title>1 CHF = 2,045.984089 BIF</title>
		<link>http://www.floatrates.com/chf/bif/</link>
		<description>1 Swiss Franc = 2,045.984089 Burundian franc</description>
		<pubDate></pubDate>
		<baseCurrency>CHF</baseCurrency>
		<baseName>Swiss Franc</baseName>
		<targetCurrency>BIF</targetCurrency>
		<targetName>Burundian franc</targetName>
		<exchangeRate>2,045.984089</exchangeRate>
		<inverseRate>0.000489</inverseRate>
		<inverseDescription>1 Burundian franc = 0.000489 Swiss Franc</inverseDescription>
	</item>
	<item>
		<title>1 CHF = 621.307768 XAF</title>
		<link>http://www.floatrates.com/chf/xaf/</link>
		<description>1 Swiss Franc = 621.307768 Central African CFA Franc</description>
		<pubDate></pubDate>
		<baseCurrency>CHF</baseCurrency>
		<baseName>Swiss Franc</baseName>
		<targetCurrency>XAF</targetCurrency>
		<targetName>Central African CFA Franc</targetName>
		<exchangeRate>621.307768</exchangeRate>
		<inverseRate>0.001610</inverseRate>
		<inverseDescription>1 Central African CFA Franc = 0.001610 Swiss Franc</inverseDescription>
	</item>
	<item>
		<title>1 CHF = 112.362137 XPF</title>
		<link>http://www.floatrates.com/chf/xpf/</link>
		<description>1 Swiss Franc = 112.362137 CFP Franc</description>
		<pubDate></pubDate>
		<baseCurrency>CHF</baseCurrency>
		<baseName>Swiss Franc</baseName>
		<targetCurrency>XPF</targetCurrency>
		<targetName>CFP Franc</targetName>
		<exchangeRate>112.362137</exchangeRate>
		<inverseRate>0.008900</inverseRate>
		<inverseDescription>1 CFP Franc = 0.008900 Swiss Franc</inverseDescription>
	</item>
	<item>
		<title>1 CHF = 189.231931 DJF</title>
		<link>http://www.floatrates.com/chf/djf/</link>
		<description>1 Swiss Franc = 189.231931 Djiboutian franc</description>
		<pubDate></pubDate>
		<baseCurrency>CHF</baseCurrency>
		<baseName>Swiss Franc</baseName>
		<targetCurrency>DJF</targetCurrency>
		<targetName>Djiboutian franc</targetName>
		<exchangeRate>189.231931</exchangeRate>
		<inverseRate>0.005285</inverseRate>
		<inverseDescription>1 Djiboutian franc = 0.005285 Swiss Franc</inverseDescription>
	</item>
	<item>
		<title>1 CHF = 10,249.832699 GNF</title>
		<link>http://www.floatrates.com/chf/gnf/</link>
		<description>1 Swiss Franc = 10,249.832699 Guinean franc</description>
		<pubDate></pubDate>
		<baseCurrency>CHF</baseCurrency>
		<baseName>Swiss Franc</baseName>
		<targetCurrency>GNF</targetCurrency>
		<targetName>Guinean franc</targetName>
		<exchangeRate>10,249.832699</exchangeRate>
		<inverseRate>0.000098</inverseRate>
		<inverseDescription>1 Guinean franc = 0.000098 Swiss Franc</inverseDescription>
	</item>
	<item>
		<title>1 CHF = 464.207299 KMF</title>
		<link>http://www.floatrates.com/chf/kmf/</link>
		<description>1 Swiss Franc = 464.207299 	Comoro franc</description>
		<pubDate></pubDate>
		<baseCurrency>CHF</baseCurrency>
		<baseName>Swiss Franc</baseName>
		<targetCurrency>KMF</targetCurrency>
		<targetName>	Comoro franc</targetName>
		<exchangeRate>464.207299</exchangeRate>
		<inverseRate>0.002154</inverseRate>
		<inverseDescription>1 	Comoro franc = 0.002154 Swiss Franc</inverseDescription>
	</item>
	<item>
		<title>1 CHF = 2,076.235209 CDF</title>
		<link>http://www.floatrates.com/chf/cdf/</link>
		<description>1 Swiss Franc = 2,076.235209 Congolese franc</description>
		<pubDate></pubDate>
		<baseCurrency>CHF</baseCurrency>
		<baseName>Swiss Franc</baseName>
		<targetCurrency>CDF</targetCurrency>
		<targetName>Congolese franc</targetName>
		<exchangeRate>2,076.235209</exchangeRate>
		<inverseRate>0.000482</inverseRate>
		<inverseDescription>1 Congolese franc = 0.000482 Swiss Franc</inverseDescription>
	</item>
	<item>
		<title>1 CHF = 1,016.083270 RWF</title>
		<link>http://www.floatrates.com/chf/rwf/</link>
		<description>1 Swiss Franc = 1,016.083270 Rwandan franc</description>
		<pubDate></pubDate>
		<baseCurrency>CHF</baseCurrency>
		<baseName>Swiss Franc</baseName>
		<targetCurrency>RWF</targetCurrency>
		<targetName>Rwandan franc</targetName>
		<exchangeRate>1,016.083270</exchangeRate>
		<inverseRate>0.000984</inverseRate>
		<inverseDescription>1 Rwandan franc = 0.000984 Swiss Franc</inverseDescription>
	</item>
	<item>
		<title>1 CHF = 172.700416 SSP</title>
		<link>http://www.floatrates.com/chf/ssp/</link>
		<description>1 Swiss Franc = 172.700416 South Sudanese pound</description>
		<pubDate></pubDate>
		<baseCurrency>CHF</baseCurrency>
		<baseName>Swiss Franc</baseName>
		<targetCurrency>SSP</targetCurrency>
		<targetName>South Sudanese pound</targetName>
		<exchangeRate>172.700416</exchangeRate>
		<inverseRate>0.005790</inverseRate>
		<inverseDescription>1 South Sudanese pound = 0.005790 Swiss Franc</inverseDescription>
	</item>
	<item>
		<title>1 CHF = 58.590838 SDG</title>
		<link>http://www.floatrates.com/chf/sdg/</link>
		<description>1 Swiss Franc = 58.590838 Sudanese pound</description>
		<pubDate></pubDate>
		<baseCurrency>CHF</baseCurrency>
		<baseName>Swiss Franc</baseName>
		<targetCurrency>SDG</targetCurrency>
		<targetName>Sudanese pound</targetName>
		<exchangeRate>58.590838</exchangeRate>
		<inverseRate>0.017068</inverseRate>
		<inverseDescription>1 Sudanese pound = 0.017068 Swiss Franc</inverseDescription>
	</item>
	<item>
		<title>1 CHF = 1,316.462887 SYP</title>
		<link>http://www.floatrates.com/chf/syp/</link>
		<description>1 Swiss Franc = 1,316.462887 Syrian pound</description>
		<pubDate></pubDate>
		<baseCurrency>CHF</baseCurrency>
		<baseName>Swiss Franc</baseName>
		<targetCurrency>SYP</targetCurrency>
		<targetName>Syrian pound</targetName>
		<exchangeRate>1,316.462887</exchangeRate>
		<inverseRate>0.000760</inverseRate>
		<inverseDescription>1 Syrian pound = 0.000760 Swiss Franc</inverseDescription>
	</item>
	<item>
		<title>1 CHF = 6.180591 GHS</title>
		<link>http://www.floatrates.com/chf/ghs/</link>
		<description>1 Swiss Franc = 6.180591 Ghanaian Cedi</description>
		<pubDate></pubDate>
		<baseCurrency>CHF</baseCurrency>
		<baseName>Swiss Franc</baseName>
		<targetCurrency>GHS</targetCurrency>
		<targetName>Ghanaian Cedi</targetName>
		<exchangeRate>6.180591</exchangeRate>
		<inverseRate>0.161797</inverseRate>
		<inverseDescription>1 Ghanaian Cedi = 0.161797 Swiss Franc</inverseDescription>
	</item>
	<item>
		<title>1 CHF = 116.372410 HTG</title>
		<link>http://www.floatrates.com/chf/htg/</link>
		<description>1 Swiss Franc = 116.372410 Haitian gourde</description>
		<pubDate></pubDate>
		<baseCurrency>CHF</baseCurrency>
		<baseName>Swiss Franc</baseName>
		<targetCurrency>HTG</targetCurrency>
		<targetName>Haitian gourde</targetName>
		<exchangeRate>116.372410</exchangeRate>
		<inverseRate>0.008593</inverseRate>
		<inverseDescription>1 Haitian gourde = 0.008593 Swiss Franc</inverseDescription>
	</item>
	<item>
		<title>1 CHF = 7,265.608493 PYG</title>
		<link>http://www.floatrates.com/chf/pyg/</link>
		<description>1 Swiss Franc = 7,265.608493 Paraguayan Guaraní</description>
		<pubDate></pubDate>
		<baseCurrency>CHF</baseCurrency>
		<baseName>Swiss Franc</baseName>
		<targetCurrency>PYG</targetCurrency>
		<targetName>Paraguayan Guaraní</targetName>
		<exchangeRate>7,265.608493</exchangeRate>
		<inverseRate>0.000138</inverseRate>
		<inverseDescription>1 Paraguayan Guaraní = 0.000138 Swiss Franc</inverseDescription>
	</item>
	<item>
		<title>1 CHF = 1.908004 ANG</title>
		<link>http://www.floatrates.com/chf/ang/</link>
		<description>1 Swiss Franc = 1.908004 Neth. Antillean Guilder</description>
		<pubDate></pubDate>
		<baseCurrency>CHF</baseCurrency>
		<baseName>Swiss Franc</baseName>
		<targetCurrency>ANG</targetCurrency>
		<targetName>Neth. Antillean Guilder</targetName>
		<exchangeRate>1.908004</exchangeRate>
		<inverseRate>0.524108</inverseRate>
		<inverseDescription>1 Neth. Antillean Guilder = 0.524108 Swiss Franc</inverseDescription>
	</item>
	<item>
		<title>1 CHF = 9,596.084827 LAK</title>
		<link>http://www.floatrates.com/chf/lak/</link>
		<description>1 Swiss Franc = 9,596.084827 Lao kip</description>
		<pubDate></pubDate>
		<baseCurrency>CHF</baseCurrency>
		<baseName>Swiss Franc</baseName>
		<targetCurrency>LAK</targetCurrency>
		<targetName>Lao kip</targetName>
		<exchangeRate>9,596.084827</exchangeRate>
		<inverseRate>0.000104</inverseRate>
		<inverseDescription>1 Lao kip = 0.000104 Swiss Franc</inverseDescription>
	</item>
	<item>
		<title>1 CHF = 781.138743 MWK</title>
		<link>http://www.floatrates.com/chf/mwk/</link>
		<description>1 Swiss Franc = 781.138743 Malawian kwacha</description>
		<pubDate></pubDate>
		<baseCurrency>CHF</baseCurrency>
		<baseName>Swiss Franc</baseName>
		<targetCurrency>MWK</targetCurrency>
		<targetName>Malawian kwacha</targetName>
		<exchangeRate>781.138743</exchangeRate>
		<inverseRate>0.001280</inverseRate>
		<inverseDescription>1 Malawian kwacha = 0.001280 Swiss Franc</inverseDescription>
	</item>
	<item>
		<title>1 CHF = 19.105130 ZMW</title>
		<link>http://www.floatrates.com/chf/zmw/</link>
		<description>1 Swiss Franc = 19.105130 Zambian kwacha</description>
		<pubDate></pubDate>
		<baseCurrency>CHF</baseCurrency>
		<baseName>Swiss Franc</baseName>
		<targetCurrency>ZMW</targetCurrency>
		<targetName>Zambian kwacha</targetName>
		<exchangeRate>19.105130</exchangeRate>
		<inverseRate>0.052342</inverseRate>
		<inverseDescription>1 Zambian kwacha = 0.052342 Swiss Franc</inverseDescription>
	</item>
	<item>
		<title>1 CHF = 610.533513 AOA</title>
		<link>http://www.floatrates.com/chf/aoa/</link>
		<description>1 Swiss Franc = 610.533513 Angolan kwanza</description>
		<pubDate></pubDate>
		<baseCurrency>CHF</baseCurrency>
		<baseName>Swiss Franc</baseName>
		<targetCurrency>AOA</targetCurrency>
		<targetName>Angolan kwanza</targetName>
		<exchangeRate>610.533513</exchangeRate>
		<inverseRate>0.001638</inverseRate>
		<inverseDescription>1 Angolan kwanza = 0.001638 Swiss Franc</inverseDescription>
	</item>
	<item>
		<title>1 CHF = 1,457.675169 MMK</title>
		<link>http://www.floatrates.com/chf/mmk/</link>
		<description>1 Swiss Franc = 1,457.675169 Myanma Kyat</description>
		<pubDate></pubDate>
		<baseCurrency>CHF</baseCurrency>
		<baseName>Swiss Franc</baseName>
		<targetCurrency>MMK</targetCurrency>
		<targetName>Myanma Kyat</targetName>
		<exchangeRate>1,457.675169</exchangeRate>
		<inverseRate>0.000686</inverseRate>
		<inverseDescription>1 Myanma Kyat = 0.000686 Swiss Franc</inverseDescription>
	</item>
	<item>
		<title>1 CHF = 3.264623 GEL</title>
		<link>http://www.floatrates.com/chf/gel/</link>
		<description>1 Swiss Franc = 3.264623 Georgian lari</description>
		<pubDate></pubDate>
		<baseCurrency>CHF</baseCurrency>
		<baseName>Swiss Franc</baseName>
		<targetCurrency>GEL</targetCurrency>
		<targetName>Georgian lari</targetName>
		<exchangeRate>3.264623</exchangeRate>
		<inverseRate>0.306314</inverseRate>
		<inverseDescription>1 Georgian lari = 0.306314 Swiss Franc</inverseDescription>
	</item>
	<item>
		<title>1 CHF = 18.281103 MDL</title>
		<link>http://www.floatrates.com/chf/mdl/</link>
		<description>1 Swiss Franc = 18.281103 Moldova Lei</description>
		<pubDate></pubDate>
		<baseCurrency>CHF</baseCurrency>
		<baseName>Swiss Franc</baseName>
		<targetCurrency>MDL</targetCurrency>
		<targetName>Moldova Lei</targetName>
		<exchangeRate>18.281103</exchangeRate>
		<inverseRate>0.054701</inverseRate>
		<inverseDescription>1 Moldova Lei = 0.054701 Swiss Franc</inverseDescription>
	</item>
	<item>
		<title>1 CHF = 116.924734 ALL</title>
		<link>http://www.floatrates.com/chf/all/</link>
		<description>1 Swiss Franc = 116.924734 Albanian lek</description>
		<pubDate></pubDate>
		<baseCurrency>CHF</baseCurrency>
		<baseName>Swiss Franc</baseName>
		<targetCurrency>ALL</targetCurrency>
		<targetName>Albanian lek</targetName>
		<exchangeRate>116.924734</exchangeRate>
		<inverseRate>0.008553</inverseRate>
		<inverseDescription>1 Albanian lek = 0.008553 Swiss Franc</inverseDescription>
	</item>
	<item>
		<title>1 CHF = 26.312812 HNL</title>
		<link>http://www.floatrates.com/chf/hnl/</link>
		<description>1 Swiss Franc = 26.312812 Honduran Lempira</description>
		<pubDate></pubDate>
		<baseCurrency>CHF</baseCurrency>
		<baseName>Swiss Franc</baseName>
		<targetCurrency>HNL</targetCurrency>
		<targetName>Honduran Lempira</targetName>
		<exchangeRate>26.312812</exchangeRate>
		<inverseRate>0.038004</inverseRate>
		<inverseDescription>1 Honduran Lempira = 0.038004 Swiss Franc</inverseDescription>
	</item>
	<item>
		<title>1 CHF = 10,350.568155 SLL</title>
		<link>http://www.floatrates.com/chf/sll/</link>
		<description>1 Swiss Franc = 10,350.568155 Sierra Leonean leone</description>
		<pubDate></pubDate>
		<baseCurrency>CHF</baseCurrency>
		<baseName>Swiss Franc</baseName>
		<targetCurrency>SLL</targetCurrency>
		<targetName>Sierra Leonean leone</targetName>
		<exchangeRate>10,350.568155</exchangeRate>
		<inverseRate>0.000097</inverseRate>
		<inverseDescription>1 Sierra Leonean leone = 0.000097 Swiss Franc</inverseDescription>
	</item>
	<item>
		<title>1 CHF = 18.126856 SZL</title>
		<link>http://www.floatrates.com/chf/szl/</link>
		<description>1 Swiss Franc = 18.126856 Swazi lilangeni</description>
		<pubDate></pubDate>
		<baseCurrency>CHF</baseCurrency>
		<baseName>Swiss Franc</baseName>
		<targetCurrency>SZL</targetCurrency>
		<targetName>Swazi lilangeni</targetName>
		<exchangeRate>18.126856</exchangeRate>
		<inverseRate>0.055167</inverseRate>
		<inverseDescription>1 Swazi lilangeni = 0.055167 Swiss Franc</inverseDescription>
	</item>
	<item>
		<title>1 CHF = 18.126856 LSL</title>
		<link>http://www.floatrates.com/chf/lsl/</link>
		<description>1 Swiss Franc = 18.126856 Lesotho loti</description>
		<pubDate></pubDate>
		<baseCurrency>CHF</baseCurrency>
		<baseName>Swiss Franc</baseName>
		<targetCurrency>LSL</targetCurrency>
		<targetName>Lesotho loti</targetName>
		<exchangeRate>18.126856</exchangeRate>
		<inverseRate>0.055167</inverseRate>
		<inverseDescription>1 Lesotho loti = 0.055167 Swiss Franc</inverseDescription>
	</item>
	<item>
		<title>1 CHF = 1.807491 AZN</title>
		<link>http://www.floatrates.com/chf/azn/</link>
		<description>1 Swiss Franc = 1.807491 Azerbaijan Manat</description>
		<pubDate></pubDate>
		<baseCurrency>CHF</baseCurrency>
		<baseName>Swiss Franc</baseName>
		<targetCurrency>AZN</targetCurrency>
		<targetName>Azerbaijan Manat</targetName>
		<exchangeRate>1.807491</exchangeRate>
		<inverseRate>0.553253</inverseRate>
		<inverseDescription>1 Azerbaijan Manat = 0.553253 Swiss Franc</inverseDescription>
	</item>
	<item>
		<title>1 CHF = 74.166923 MZN</title>
		<link>http://www.floatrates.com/chf/mzn/</link>
		<description>1 Swiss Franc = 74.166923 Mozambican metical</description>
		<pubDate></pubDate>
		<baseCurrency>CHF</baseCurrency>
		<baseName>Swiss Franc</baseName>
		<targetCurrency>MZN</targetCurrency>
		<targetName>Mozambican metical</targetName>
		<exchangeRate>74.166923</exchangeRate>
		<inverseRate>0.013483</inverseRate>
		<inverseDescription>1 Mozambican metical = 0.013483 Swiss Franc</inverseDescription>
	</item>
	<item>
		<title>1 CHF = 383.899216 NGN</title>
		<link>http://www.floatrates.com/chf/ngn/</link>
		<description>1 Swiss Franc = 383.899216 Nigerian Naira</description>
		<pubDate></pubDate>
		<baseCurrency>CHF</baseCurrency>
		<baseName>Swiss Franc</baseName>
		<targetCurrency>NGN</targetCurrency>
		<targetName>Nigerian Naira</targetName>
		<exchangeRate>383.899216</exchangeRate>
		<inverseRate>0.002605</inverseRate>
		<inverseDescription>1 Nigerian Naira = 0.002605 Swiss Franc</inverseDescription>
	</item>
	<item>
		<title>1 CHF = 16.023892 ERN</title>
		<link>http://www.floatrates.com/chf/ern/</link>
		<description>1 Swiss Franc = 16.023892 Eritrean nakfa</description>
		<pubDate></pubDate>
		<baseCurrency>CHF</baseCurrency>
		<baseName>Swiss Franc</baseName>
		<targetCurrency>ERN</targetCurrency>
		<targetName>Eritrean nakfa</targetName>
		<exchangeRate>16.023892</exchangeRate>
		<inverseRate>0.062407</inverseRate>
		<inverseDescription>1 Eritrean nakfa = 0.062407 Swiss Franc</inverseDescription>
	</item>
	<item>
		<title>1 CHF = 3.728907 TMT</title>
		<link>http://www.floatrates.com/chf/tmt/</link>
		<description>1 Swiss Franc = 3.728907 New Turkmenistan Manat</description>
		<pubDate></pubDate>
		<baseCurrency>CHF</baseCurrency>
		<baseName>Swiss Franc</baseName>
		<targetCurrency>TMT</targetCurrency>
		<targetName>New Turkmenistan Manat</targetName>
		<exchangeRate>3.728907</exchangeRate>
		<inverseRate>0.268175</inverseRate>
		<inverseDescription>1 New Turkmenistan Manat = 0.268175 Swiss Franc</inverseDescription>
	</item>
	<item>
		<title>1 CHF = 40.939565 MRU</title>
		<link>http://www.floatrates.com/chf/mru/</link>
		<description>1 Swiss Franc = 40.939565 Mauritanian ouguiya</description>
		<pubDate></pubDate>
		<baseCurrency>CHF</baseCurrency>
		<baseName>Swiss Franc</baseName>
		<targetCurrency>MRU</targetCurrency>
		<targetName>Mauritanian ouguiya</targetName>
		<exchangeRate>40.939565</exchangeRate>
		<inverseRate>0.024426</inverseRate>
		<inverseDescription>1 Mauritanian ouguiya = 0.024426 Swiss Franc</inverseDescription>
	</item>
	<item>
		<title>1 CHF = 2.419969 TOP</title>
		<link>http://www.floatrates.com/chf/top/</link>
		<description>1 Swiss Franc = 2.419969 Tongan paʻanga</description>
		<pubDate></pubDate>
		<baseCurrency>CHF</baseCurrency>
		<baseName>Swiss Franc</baseName>
		<targetCurrency>TOP</targetCurrency>
		<targetName>Tongan paʻanga</targetName>
		<exchangeRate>2.419969</exchangeRate>
		<inverseRate>0.413229</inverseRate>
		<inverseDescription>1 Tongan paʻanga = 0.413229 Swiss Franc</inverseDescription>
	</item>
	<item>
		<title>1 CHF = 8.484756 MOP</title>
		<link>http://www.floatrates.com/chf/mop/</link>
		<description>1 Swiss Franc = 8.484756 Macanese pataca</description>
		<pubDate></pubDate>
		<baseCurrency>CHF</baseCurrency>
		<baseName>Swiss Franc</baseName>
		<targetCurrency>MOP</targetCurrency>
		<targetName>Macanese pataca</targetName>
		<exchangeRate>8.484756</exchangeRate>
		<inverseRate>0.117858</inverseRate>
		<inverseDescription>1 Macanese pataca = 0.117858 Swiss Franc</inverseDescription>
	</item>
	<item>
		<title>1 CHF = 75.362052 ARS</title>
		<link>http://www.floatrates.com/chf/ars/</link>
		<description>1 Swiss Franc = 75.362052 Argentine Peso</description>
		<pubDate></pubDate>
		<baseCurrency>CHF</baseCurrency>
		<baseName>Swiss Franc</baseName>
		<targetCurrency>ARS</targetCurrency>
		<targetName>Argentine Peso</targetName>
		<exchangeRate>75.362052</exchangeRate>
		<inverseRate>0.013269</inverseRate>
		<inverseDescription>1 Argentine Peso = 0.013269 Swiss Franc</inverseDescription>
	</item>
	<item>
		<title>1 CHF = 61.951195 DOP</title>
		<link>http://www.floatrates.com/chf/dop/</link>
		<description>1 Swiss Franc = 61.951195 Dominican Peso</description>
		<pubDate></pubDate>
		<baseCurrency>CHF</baseCurrency>
		<baseName>Swiss Franc</baseName>
		<targetCurrency>DOP</targetCurrency>
		<targetName>Dominican Peso</targetName>
		<exchangeRate>61.951195</exchangeRate>
		<inverseRate>0.016142</inverseRate>
		<inverseDescription>1 Dominican Peso = 0.016142 Swiss Franc</inverseDescription>
	</item>
	<item>
		<title>1 CHF = 1.062038 CUP</title>
		<link>http://www.floatrates.com/chf/cup/</link>
		<description>1 Swiss Franc = 1.062038 Cuban peso</description>
		<pubDate></pubDate>
		<baseCurrency>CHF</baseCurrency>
		<baseName>Swiss Franc</baseName>
		<targetCurrency>CUP</targetCurrency>
		<targetName>Cuban peso</targetName>
		<exchangeRate>1.062038</exchangeRate>
		<inverseRate>0.941586</inverseRate>
		<inverseDescription>1 Cuban peso = 0.941586 Swiss Franc</inverseDescription>
	</item>
	<item>
		<title>1 CHF = 45.932029 UYU</title>
		<link>http://www.floatrates.com/chf/uyu/</link>
		<description>1 Swiss Franc = 45.932029 Uruguayan Peso</description>
		<pubDate></pubDate>
		<baseCurrency>CHF</baseCurrency>
		<baseName>Swiss Franc</baseName>
		<targetCurrency>UYU</targetCurrency>
		<targetName>Uruguayan Peso</targetName>
		<exchangeRate>45.932029</exchangeRate>
		<inverseRate>0.021771</inverseRate>
		<inverseDescription>1 Uruguayan Peso = 0.021771 Swiss Franc</inverseDescription>
	</item>
	<item>
		<title>1 CHF = 8.184731 GTQ</title>
		<link>http://www.floatrates.com/chf/gtq/</link>
		<description>1 Swiss Franc = 8.184731 Guatemalan Quetzal</description>
		<pubDate></pubDate>
		<baseCurrency>CHF</baseCurrency>
		<baseName>Swiss Franc</baseName>
		<targetCurrency>GTQ</targetCurrency>
		<targetName>Guatemalan Quetzal</targetName>
		<exchangeRate>8.184731</exchangeRate>
		<inverseRate>0.122179</inverseRate>
		<inverseDescription>1 Guatemalan Quetzal = 0.122179 Swiss Franc</inverseDescription>
	</item>
	<item>
		<title>1 CHF = 44,958.752264 IRR</title>
		<link>http://www.floatrates.com/chf/irr/</link>
		<description>1 Swiss Franc = 44,958.752264 Iranian rial</description>
		<pubDate></pubDate>
		<baseCurrency>CHF</baseCurrency>
		<baseName>Swiss Franc</baseName>
		<targetCurrency>IRR</targetCurrency>
		<targetName>Iranian rial</targetName>
		<exchangeRate>44,958.752264</exchangeRate>
		<inverseRate>0.000022</inverseRate>
		<inverseDescription>1 Iranian rial = 0.000022 Swiss Franc</inverseDescription>
	</item>
	<item>
		<title>1 CHF = 265.851397 YER</title>
		<link>http://www.floatrates.com/chf/yer/</link>
		<description>1 Swiss Franc = 265.851397 Yemeni rial</description>
		<pubDate></pubDate>
		<baseCurrency>CHF</baseCurrency>
		<baseName>Swiss Franc</baseName>
		<targetCurrency>YER</targetCurrency>
		<targetName>Yemeni rial</targetName>
		<exchangeRate>265.851397</exchangeRate>
		<inverseRate>0.003761</inverseRate>
		<inverseDescription>1 Yemeni rial = 0.003761 Swiss Franc</inverseDescription>
	</item>
	<item>
		<title>1 CHF = 4,356.443888 KHR</title>
		<link>http://www.floatrates.com/chf/khr/</link>
		<description>1 Swiss Franc = 4,356.443888 Cambodian riel</description>
		<pubDate></pubDate>
		<baseCurrency>CHF</baseCurrency>
		<baseName>Swiss Franc</baseName>
		<targetCurrency>KHR</targetCurrency>
		<targetName>Cambodian riel</targetName>
		<exchangeRate>4,356.443888</exchangeRate>
		<inverseRate>0.000230</inverseRate>
		<inverseDescription>1 Cambodian riel = 0.000230 Swiss Franc</inverseDescription>
	</item>
	<item>
		<title>1 CHF = 2.580988 BYN</title>
		<link>http://www.floatrates.com/chf/byn/</link>
		<description>1 Swiss Franc = 2.580988 Belarussian Ruble</description>
		<pubDate></pubDate>
		<baseCurrency>CHF</baseCurrency>
		<baseName>Swiss Franc</baseName>
		<targetCurrency>BYN</targetCurrency>
		<targetName>Belarussian Ruble</targetName>
		<exchangeRate>2.580988</exchangeRate>
		<inverseRate>0.387448</inverseRate>
		<inverseDescription>1 Belarussian Ruble = 0.387448 Swiss Franc</inverseDescription>
	</item>
	<item>
		<title>1 CHF = 197.491034 LKR</title>
		<link>http://www.floatrates.com/chf/lkr/</link>
		<description>1 Swiss Franc = 197.491034 Sri Lanka Rupee</description>
		<pubDate></pubDate>
		<baseCurrency>CHF</baseCurrency>
		<baseName>Swiss Franc</baseName>
		<targetCurrency>LKR</targetCurrency>
		<targetName>Sri Lanka Rupee</targetName>
		<exchangeRate>197.491034</exchangeRate>
		<inverseRate>0.005064</inverseRate>
		<inverseDescription>1 Sri Lanka Rupee = 0.005064 Swiss Franc</inverseDescription>
	</item>
	<item>
		<title>1 CHF = 16.430114 MVR</title>
		<link>http://www.floatrates.com/chf/mvr/</link>
		<description>1 Swiss Franc = 16.430114 Maldivian rufiyaa</description>
		<pubDate></pubDate>
		<baseCurrency>CHF</baseCurrency>
		<baseName>Swiss Franc</baseName>
		<targetCurrency>MVR</targetCurrency>
		<targetName>Maldivian rufiyaa</targetName>
		<exchangeRate>16.430114</exchangeRate>
		<inverseRate>0.060864</inverseRate>
		<inverseDescription>1 Maldivian rufiyaa = 0.060864 Swiss Franc</inverseDescription>
	</item>
	<item>
		<title>1 CHF = 127.583550 NPR</title>
		<link>http://www.floatrates.com/chf/npr/</link>
		<description>1 Swiss Franc = 127.583550 Nepalese Rupee</description>
		<pubDate></pubDate>
		<baseCurrency>CHF</baseCurrency>
		<baseName>Swiss Franc</baseName>
		<targetCurrency>NPR</targetCurrency>
		<targetName>Nepalese Rupee</targetName>
		<exchangeRate>127.583550</exchangeRate>
		<inverseRate>0.007838</inverseRate>
		<inverseDescription>1 Nepalese Rupee = 0.007838 Swiss Franc</inverseDescription>
	</item>
	<item>
		<title>1 CHF = 177.378893 PKR</title>
		<link>http://www.floatrates.com/chf/pkr/</link>
		<description>1 Swiss Franc = 177.378893 Pakistani Rupee</description>
		<pubDate></pubDate>
		<baseCurrency>CHF</baseCurrency>
		<baseName>Swiss Franc</baseName>
		<targetCurrency>PKR</targetCurrency>
		<targetName>Pakistani Rupee</targetName>
		<exchangeRate>177.378893</exchangeRate>
		<inverseRate>0.005638</inverseRate>
		<inverseDescription>1 Pakistani Rupee = 0.005638 Swiss Franc</inverseDescription>
	</item>
	<item>
		<title>1 CHF = 18.706400 SCR</title>
		<link>http://www.floatrates.com/chf/scr/</link>
		<description>1 Swiss Franc = 18.706400 Seychelles rupee</description>
		<pubDate></pubDate>
		<baseCurrency>CHF</baseCurrency>
		<baseName>Swiss Franc</baseName>
		<targetCurrency>SCR</targetCurrency>
		<targetName>Seychelles rupee</targetName>
		<exchangeRate>18.706400</exchangeRate>
		<inverseRate>0.053458</inverseRate>
		<inverseDescription>1 Seychelles rupee = 0.053458 Swiss Franc</inverseDescription>
	</item>
	<item>
		<title>1 CHF = 3.726444 PEN</title>
		<link>http://www.floatrates.com/chf/pen/</link>
		<description>1 Swiss Franc = 3.726444 Peruvian Nuevo Sol</description>
		<pubDate></pubDate>
		<baseCurrency>CHF</baseCurrency>
		<baseName>Swiss Franc</baseName>
		<targetCurrency>PEN</targetCurrency>
		<targetName>Peruvian Nuevo Sol</targetName>
		<exchangeRate>3.726444</exchangeRate>
		<inverseRate>0.268352</inverseRate>
		<inverseDescription>1 Peruvian Nuevo Sol = 0.268352 Swiss Franc</inverseDescription>
	</item>
	<item>
		<title>1 CHF = 82.298876 KGS</title>
		<link>http://www.floatrates.com/chf/kgs/</link>
		<description>1 Swiss Franc = 82.298876 Kyrgyzstan Som</description>
		<pubDate></pubDate>
		<baseCurrency>CHF</baseCurrency>
		<baseName>Swiss Franc</baseName>
		<targetCurrency>KGS</targetCurrency>
		<targetName>Kyrgyzstan Som</targetName>
		<exchangeRate>82.298876</exchangeRate>
		<inverseRate>0.012151</inverseRate>
		<inverseDescription>1 Kyrgyzstan Som = 0.012151 Swiss Franc</inverseDescription>
	</item>
	<item>
		<title>1 CHF = 10.992762 TJS</title>
		<link>http://www.floatrates.com/chf/tjs/</link>
		<description>1 Swiss Franc = 10.992762 Tajikistan Ruble</description>
		<pubDate></pubDate>
		<baseCurrency>CHF</baseCurrency>
		<baseName>Swiss Franc</baseName>
		<targetCurrency>TJS</targetCurrency>
		<targetName>Tajikistan Ruble</targetName>
		<exchangeRate>10.992762</exchangeRate>
		<inverseRate>0.090969</inverseRate>
		<inverseDescription>1 Tajikistan Ruble = 0.090969 Swiss Franc</inverseDescription>
	</item>
	<item>
		<title>1 CHF = 10,860.260544 UZS</title>
		<link>http://www.floatrates.com/chf/uzs/</link>
		<description>1 Swiss Franc = 10,860.260544 Uzbekistan Sum</description>
		<pubDate></pubDate>
		<baseCurrency>CHF</baseCurrency>
		<baseName>Swiss Franc</baseName>
		<targetCurrency>UZS</targetCurrency>
		<targetName>Uzbekistan Sum</targetName>
		<exchangeRate>10,860.260544</exchangeRate>
		<inverseRate>0.000092</inverseRate>
		<inverseDescription>1 Uzbekistan Sum = 0.000092 Swiss Franc</inverseDescription>
	</item>
	<item>
		<title>1 CHF = 113.576912 KES</title>
		<link>http://www.floatrates.com/chf/kes/</link>
		<description>1 Swiss Franc = 113.576912 Kenyan shilling</description>
		<pubDate></pubDate>
		<baseCurrency>CHF</baseCurrency>
		<baseName>Swiss Franc</baseName>
		<targetCurrency>KES</targetCurrency>
		<targetName>Kenyan shilling</targetName>
		<exchangeRate>113.576912</exchangeRate>
		<inverseRate>0.008805</inverseRate>
		<inverseDescription>1 Kenyan shilling = 0.008805 Swiss Franc</inverseDescription>
	</item>
	<item>
		<title>1 CHF = 614.900195 SOS</title>
		<link>http://www.floatrates.com/chf/sos/</link>
		<description>1 Swiss Franc = 614.900195 Somali shilling</description>
		<pubDate></pubDate>
		<baseCurrency>CHF</baseCurrency>
		<baseName>Swiss Franc</baseName>
		<targetCurrency>SOS</targetCurrency>
		<targetName>Somali shilling</targetName>
		<exchangeRate>614.900195</exchangeRate>
		<inverseRate>0.001626</inverseRate>
		<inverseDescription>1 Somali shilling = 0.001626 Swiss Franc</inverseDescription>
	</item>
	<item>
		<title>1 CHF = 2,463.556280 TZS</title>
		<link>http://www.floatrates.com/chf/tzs/</link>
		<description>1 Swiss Franc = 2,463.556280 Tanzanian shilling</description>
		<pubDate></pubDate>
		<baseCurrency>CHF</baseCurrency>
		<baseName>Swiss Franc</baseName>
		<targetCurrency>TZS</targetCurrency>
		<targetName>Tanzanian shilling</targetName>
		<exchangeRate>2,463.556280</exchangeRate>
		<inverseRate>0.000406</inverseRate>
		<inverseDescription>1 Tanzanian shilling = 0.000406 Swiss Franc</inverseDescription>
	</item>
	<item>
		<title>1 CHF = 3,955.569239 UGX</title>
		<link>http://www.floatrates.com/chf/ugx/</link>
		<description>1 Swiss Franc = 3,955.569239 Ugandan shilling</description>
		<pubDate></pubDate>
		<baseCurrency>CHF</baseCurrency>
		<baseName>Swiss Franc</baseName>
		<targetCurrency>UGX</targetCurrency>
		<targetName>Ugandan shilling</targetName>
		<exchangeRate>3,955.569239</exchangeRate>
		<inverseRate>0.000253</inverseRate>
		<inverseDescription>1 Ugandan shilling = 0.000253 Swiss Franc</inverseDescription>
	</item>
	<item>
		<title>1 CHF = 90.500546 BDT</title>
		<link>http://www.floatrates.com/chf/bdt/</link>
		<description>1 Swiss Franc = 90.500546 Bangladeshi taka</description>
		<pubDate></pubDate>
		<baseCurrency>CHF</baseCurrency>
		<baseName>Swiss Franc</baseName>
		<targetCurrency>BDT</targetCurrency>
		<targetName>Bangladeshi taka</targetName>
		<exchangeRate>90.500546</exchangeRate>
		<inverseRate>0.011050</inverseRate>
		<inverseDescription>1 Bangladeshi taka = 0.011050 Swiss Franc</inverseDescription>
	</item>
	<item>
		<title>1 CHF = 2.806022 WST</title>
		<link>http://www.floatrates.com/chf/wst/</link>
		<description>1 Swiss Franc = 2.806022 Samoan tala</description>
		<pubDate></pubDate>
		<baseCurrency>CHF</baseCurrency>
		<baseName>Swiss Franc</baseName>
		<targetCurrency>WST</targetCurrency>
		<targetName>Samoan tala</targetName>
		<exchangeRate>2.806022</exchangeRate>
		<inverseRate>0.356376</inverseRate>
		<inverseDescription>1 Samoan tala = 0.356376 Swiss Franc</inverseDescription>
	</item>
	<item>
		<title>1 CHF = 437.934481 KZT</title>
		<link>http://www.floatrates.com/chf/kzt/</link>
		<description>1 Swiss Franc = 437.934481 Kazakhstani Tenge</description>
		<pubDate></pubDate>
		<baseCurrency>CHF</baseCurrency>
		<baseName>Swiss Franc</baseName>
		<targetCurrency>KZT</targetCurrency>
		<targetName>Kazakhstani Tenge</targetName>
		<exchangeRate>437.934481</exchangeRate>
		<inverseRate>0.002283</inverseRate>
		<inverseDescription>1 Kazakhstani Tenge = 0.002283 Swiss Franc</inverseDescription>
	</item>
	<item>
		<title>1 CHF = 3,009.058028 MNT</title>
		<link>http://www.floatrates.com/chf/mnt/</link>
		<description>1 Swiss Franc = 3,009.058028 Mongolian togrog</description>
		<pubDate></pubDate>
		<baseCurrency>CHF</baseCurrency>
		<baseName>Swiss Franc</baseName>
		<targetCurrency>MNT</targetCurrency>
		<targetName>Mongolian togrog</targetName>
		<exchangeRate>3,009.058028</exchangeRate>
		<inverseRate>0.000332</inverseRate>
		<inverseDescription>1 Mongolian togrog = 0.000332 Swiss Franc</inverseDescription>
	</item>
	<item>
		<title>1 CHF = 122.089009 VUV</title>
		<link>http://www.floatrates.com/chf/vuv/</link>
		<description>1 Swiss Franc = 122.089009 Vanuatu vatu</description>
		<pubDate></pubDate>
		<baseCurrency>CHF</baseCurrency>
		<baseName>Swiss Franc</baseName>
		<targetCurrency>VUV</targetCurrency>
		<targetName>Vanuatu vatu</targetName>
		<exchangeRate>122.089009</exchangeRate>
		<inverseRate>0.008191</inverseRate>
		<inverseDescription>1 Vanuatu vatu = 0.008191 Swiss Franc</inverseDescription>
	</item>
	<item>
		<title>1 CHF = 1.846048 BAM</title>
		<link>http://www.floatrates.com/chf/bam/</link>
		<description>1 Swiss Franc = 1.846048 Bosnia and Herzegovina convertible mark</description>
		<pubDate></pubDate>
		<baseCurrency>CHF</baseCurrency>
		<baseName>Swiss Franc</baseName>
		<targetCurrency>BAM</targetCurrency>
		<targetName>Bosnia and Herzegovina convertible mark</targetName>
		<exchangeRate>1.846048</exchangeRate>
		<inverseRate>0.541698</inverseRate>
		<inverseDescription>1 Bosnia and Herzegovina convertible mark = 0.541698 Swiss Franc</inverseDescription>
	</item>
</channel>

